{"nodes":{"沙通天":{"shape":"dot","size":54,"label":"沙通天"},"黎生":{"shape":"dot","size":19,"label":"黎生"},"張十五":{"shape":"dot","size":2,"label":"張十五"},"韓小瑩":{"shape":"dot","size":59,"label":"韓小瑩"},"孫婆婆":{"shape":"dot","size":32,"label":"孫婆婆"},"赤老溫":{"shape":"dot","size":19,"label":"赤老溫"},"馬青雄":{"shape":"dot","size":18,"label":"馬青雄"},"童大海":{"shape":"dot","size":3,"label":"童大海"},"譚處端":{"shape":"dot","size":33,"label":"譚處端"},"天鳴禪師":{"shape":"dot","size":6,"label":"天鳴禪師"},"李莫愁":{"shape":"dot","size":61,"label":"李莫愁"},"窩闊台":{"shape":"dot","size":33,"label":"窩闊台"},"藍天和":{"shape":"dot","size":10,"label":"藍天和"},"九死生":{"shape":"dot","size":11,"label":"九死生"},"陸無雙":{"shape":"dot","size":47,"label":"陸無雙"},"尹志平":{"shape":"dot","size":66,"label":"尹志平"},"陳玄風":{"shape":"dot","size":53,"label":"陳玄風"},"忽必烈":{"shape":"dot","size":30,"label":"忽必烈"},"朱子柳":{"shape":"dot","size":50,"label":"朱子柳"},"歐陽克":{"shape":"dot","size":49,"label":"歐陽克"},"郭靖":{"shape":"dot","size":147,"label":"郭靖"},"張志敬":{"shape":"dot","size":17,"label":"張志敬"},"馬鈺":{"shape":"dot","size":73,"label":"馬鈺"},"博爾忽":{"shape":"dot","size":32,"label":"博爾忽"},"姜文":{"shape":"dot","size":4,"label":"姜文"},"梁子翁":{"shape":"dot","size":32,"label":"梁子翁"},"裘千尺":{"shape":"dot","size":31,"label":"裘千尺"},"王罕":{"shape":"dot","size":28,"label":"王罕"},"史孟捷":{"shape":"dot","size":16,"label":"史孟捷"},"梁長老":{"shape":"dot","size":24,"label":"梁長老"},"公孫綠萼":{"shape":"dot","size":27,"label":"公孫綠萼"},"催命鬼":{"shape":"dot","size":8,"label":"催命鬼"},"莫圖根":{"shape":"dot","size":6,"label":"莫圖根"},"耶律齊":{"shape":"dot","size":48,"label":"耶律齊"},"神雕":{"shape":"dot","size":42,"label":"神雕"},"史叔剛":{"shape":"dot","size":14,"label":"史叔剛"},"完顏萍":{"shape":"dot","size":26,"label":"完顏萍"},"史彌遠":{"shape":"dot","size":8,"label":"史彌遠"},"陸展元":{"shape":"dot","size":15,"label":"陸展元"},"曲靈風":{"shape":"dot","size":16,"label":"曲靈風"},"俏鬼":{"shape":"dot","size":10,"label":"俏鬼"},"程英":{"shape":"dot","size":42,"label":"程英"},"楊過":{"shape":"dot","size":106,"label":"楊過"},"枯木大師":{"shape":"dot","size":12,"label":"枯木大師"},"者勒米":{"shape":"dot","size":17,"label":"者勒米"},"無常鬼":{"shape":"dot","size":20,"label":"無常鬼"},"朱聰":{"shape":"dot","size":66,"label":"朱聰"},"摩訶末":{"shape":"dot","size":13,"label":"摩訶末"},"郝大通":{"shape":"dot","size":53,"label":"郝大通"},"王彥章":{"shape":"dot","size":5,"label":"王彥章"},"郭芙":{"shape":"dot","size":64,"label":"郭芙"},"劉處玄":{"shape":"dot","size":41,"label":"劉處玄"},"鹿清篤":{"shape":"dot","size":19,"label":"鹿清篤"},"曇華大師":{"shape":"dot","size":9,"label":"曇華大師"},"陸立鼎":{"shape":"dot","size":15,"label":"陸立鼎"},"術赤":{"shape":"dot","size":23,"label":"術赤"},"史伯威":{"shape":"dot","size":16,"label":"史伯威"},"趙老爵爺":{"shape":"dot","size":10,"label":"趙老爵爺"},"百草仙":{"shape":"dot","size":16,"label":"百草仙"},"上官劍南":{"shape":"dot","size":8,"label":"上官劍南"},"曲傻姑":{"shape":"dot","size":41,"label":"曲傻姑"},"察合台":{"shape":"dot","size":21,"label":"察合台"},"楊鐵心":{"shape":"dot","size":59,"label":"楊鐵心"},"吳青烈":{"shape":"dot","size":15,"label":"吳青烈"},"張一氓":{"shape":"dot","size":16,"label":"張一氓"},"魯有腳":{"shape":"dot","size":50,"label":"魯有腳"},"穆念慈":{"shape":"dot","size":56,"label":"穆念慈"},"全金發":{"shape":"dot","size":25,"label":"全金發"},"李萍":{"shape":"dot","size":27,"label":"李萍"},"周伯通":{"shape":"dot","size":87,"label":"周伯通"},"木華黎":{"shape":"dot","size":21,"label":"木華黎"},"尼摩星":{"shape":"dot","size":37,"label":"尼摩星"},"黃蓉":{"shape":"dot","size":134,"label":"黃蓉"},"大頭鬼":{"shape":"dot","size":24,"label":"大頭鬼"},"哲別":{"shape":"dot","size":48,"label":"哲別"},"祁志誠":{"shape":"dot","size":21,"label":"祁志誠"},"郭破虜":{"shape":"dot","size":13,"label":"郭破虜"},"沈青剛":{"shape":"dot","size":16,"label":"沈青剛"},"蒙哥":{"shape":"dot","size":13,"label":"蒙哥"},"何沅君":{"shape":"dot","size":13,"label":"何沅君"},"湯祖德":{"shape":"dot","size":13,"label":"湯祖德"},"李志常":{"shape":"dot","size":36,"label":"李志常"},"聖因師太":{"shape":"dot","size":16,"label":"聖因師太"},"霍都":{"shape":"dot","size":54,"label":"霍都"},"柯辟邪":{"shape":"dot","size":5,"label":"柯辟邪"},"黃裳":{"shape":"dot","size":9,"label":"黃裳"},"都史":{"shape":"dot","size":31,"label":"都史"},"皮清玄":{"shape":"dot","size":5,"label":"皮清玄"},"一燈大師":{"shape":"dot","size":68,"label":"一燈大師"},"完顏洪烈":{"shape":"dot","size":71,"label":"完顏洪烈"},"王志坦":{"shape":"dot","size":24,"label":"王志坦"},"南希仁":{"shape":"dot","size":44,"label":"南希仁"},"武三娘":{"shape":"dot","size":18,"label":"武三娘"},"武三通":{"shape":"dot","size":43,"label":"武三通"},"獨孤求敗":{"shape":"dot","size":7,"label":"獨孤求敗"},"黃藥師":{"shape":"dot","size":88,"label":"黃藥師"},"耶律燕":{"shape":"dot","size":26,"label":"耶律燕"},"華箏":{"shape":"dot","size":61,"label":"華箏"},"青靈子":{"shape":"dot","size":12,"label":"青靈子"},"梅超風":{"shape":"dot","size":64,"label":"梅超風"},"蓋運聰":{"shape":"dot","size":4,"label":"蓋運聰"},"程瑤迦":{"shape":"dot","size":33,"label":"程瑤迦"},"王道乾":{"shape":"dot","size":5,"label":"王道乾"},"馬光佐":{"shape":"dot","size":16,"label":"馬光佐"},"呂文德":{"shape":"dot","size":15,"label":"呂文德"},"樵夫":{"shape":"dot","size":3,"label":"樵夫"},"申志凡":{"shape":"dot","size":14,"label":"申志凡"},"史仲猛":{"shape":"dot","size":19,"label":"史仲猛"},"天竺神僧":{"shape":"dot","size":12,"label":"天竺神僧"},"楊康":{"shape":"dot","size":72,"label":"楊康"},"武修文":{"shape":"dot","size":43,"label":"武修文"},"討債鬼":{"shape":"dot","size":3,"label":"討債鬼"},"張志仙":{"shape":"dot","size":16,"label":"張志仙"},"孫不二":{"shape":"dot","size":55,"label":"孫不二"},"馮默風":{"shape":"dot","size":17,"label":"馮默風"},"郭嘯天":{"shape":"dot","size":25,"label":"郭嘯天"},"黃夫人":{"shape":"dot","size":15,"label":"黃夫人"},"簡長老":{"shape":"dot","size":18,"label":"簡長老"},"余兆興":{"shape":"dot","size":14,"label":"余兆興"},"耶律楚材":{"shape":"dot","size":15,"label":"耶律楚材"},"侯通海":{"shape":"dot","size":37,"label":"侯通海"},"喪門鬼":{"shape":"dot","size":10,"label":"喪門鬼"},"喬寨主":{"shape":"dot","size":3,"label":"喬寨主"},"石彥明":{"shape":"dot","size":3,"label":"石彥明"},"小龍女":{"shape":"dot","size":76,"label":"小龍女"},"柯鎮惡":{"shape":"dot","size":78,"label":"柯鎮惡"},"陸二娘":{"shape":"dot","size":11,"label":"陸二娘"},"笑臉鬼":{"shape":"dot","size":11,"label":"笑臉鬼"},"段天德":{"shape":"dot","size":33,"label":"段天德"},"姬清虛":{"shape":"dot","size":7,"label":"姬清虛"},"彭連虎":{"shape":"dot","size":52,"label":"彭連虎"},"人廚子":{"shape":"dot","size":15,"label":"人廚子"},"速不台":{"shape":"dot","size":14,"label":"速不台"},"煞神鬼":{"shape":"dot","size":6,"label":"煞神鬼"},"武敦儒":{"shape":"dot","size":34,"label":"武敦儒"},"張阿生":{"shape":"dot","size":31,"label":"張阿生"},"錢青健":{"shape":"dot","size":22,"label":"錢青健"},"洪七公":{"shape":"dot","size":74,"label":"洪七公"},"趙志敬":{"shape":"dot","size":47,"label":"趙志敬"},"樊一翁":{"shape":"dot","size":39,"label":"樊一翁"},"完顏洪熙":{"shape":"dot","size":18,"label":"完顏洪熙"},"王處一":{"shape":"dot","size":67,"label":"王處一"},"忽都虎":{"shape":"dot","size":4,"label":"忽都虎"},"鐵木真":{"shape":"dot","size":74,"label":"鐵木真"},"瑛姑":{"shape":"dot","size":44,"label":"瑛姑"},"王重陽":{"shape":"dot","size":53,"label":"王重陽"},"桑昆":{"shape":"dot","size":28,"label":"桑昆"},"點蒼漁隱":{"shape":"dot","size":16,"label":"點蒼漁隱"},"包惜弱":{"shape":"dot","size":31,"label":"包惜弱"},"林朝英":{"shape":"dot","size":19,"label":"林朝英"},"焦木大師":{"shape":"dot","size":16,"label":"焦木大師"},"裘千仞":{"shape":"dot","size":81,"label":"裘千仞"},"金輪法王":{"shape":"dot","size":64,"label":"金輪法王"},"歐陽鋒":{"shape":"dot","size":79,"label":"歐陽鋒"},"史季強":{"shape":"dot","size":16,"label":"史季強"},"達爾巴":{"shape":"dot","size":35,"label":"達爾巴"},"吊死鬼":{"shape":"dot","size":12,"label":"吊死鬼"},"洪凌波":{"shape":"dot","size":18,"label":"洪凌波"},"郭襄":{"shape":"dot","size":70,"label":"郭襄"},"瀟湘子":{"shape":"dot","size":36,"label":"瀟湘子"},"博爾術":{"shape":"dot","size":35,"label":"博爾術"},"尹克西":{"shape":"dot","size":30,"label":"尹克西"},"韓寶駒":{"shape":"dot","size":51,"label":"韓寶駒"},"狗肉頭陀":{"shape":"dot","size":9,"label":"狗肉頭陀"},"拖雷":{"shape":"dot","size":66,"label":"拖雷"},"靈智上人":{"shape":"dot","size":31,"label":"靈智上人"},"彭長老":{"shape":"dot","size":27,"label":"彭長老"},"聾啞頭陀":{"shape":"dot","size":9,"label":"聾啞頭陀"},"裘千丈":{"shape":"dot","size":24,"label":"裘千丈"},"韓無垢":{"shape":"dot","size":10,"label":"韓無垢"},"陸冠英":{"shape":"dot","size":51,"label":"陸冠英"},"陸乘風":{"shape":"dot","size":40,"label":"陸乘風"},"丘處機":{"shape":"dot","size":90,"label":"丘處機"},"簡管家":{"shape":"dot","size":11,"label":"簡管家"},"公孫止":{"shape":"dot","size":36,"label":"公孫止"}},"edges":{"沙通天":{"李志常":{"weight":1},"完顏洪烈":{"weight":27},"王志坦":{"weight":1},"南希仁":{"weight":3},"韓小瑩":{"weight":3},"黃藥師":{"weight":8},"馬青雄":{"weight":3},"譚處端":{"weight":1},"梅超風":{"weight":10},"尹志平":{"weight":1},"陳玄風":{"weight":4},"程瑤迦":{"weight":1},"郭靖":{"weight":55},"歐陽克":{"weight":26},"張志敬":{"weight":1},"馬鈺":{"weight":10},"楊康":{"weight":23},"梁子翁":{"weight":40},"張志仙":{"weight":1},"孫不二":{"weight":1},"侯通海":{"weight":45},"柯鎮惡":{"weight":16},"彭連虎":{"weight":73},"楊過":{"weight":4},"張阿生":{"weight":1},"錢青健":{"weight":2},"洪七公":{"weight":15},"趙志敬":{"weight":1},"無常鬼":{"weight":1},"朱聰":{"weight":10},"王處一":{"weight":18},"鐵木真":{"weight":1},"王重陽":{"weight":3},"包惜弱":{"weight":1},"郝大通":{"weight":1},"焦木大師":{"weight":1},"劉處玄":{"weight":1},"裘千仞":{"weight":7},"歐陽鋒":{"weight":23},"曲傻姑":{"weight":2},"楊鐵心":{"weight":5},"吳青烈":{"weight":1},"韓寶駒":{"weight":4},"靈智上人":{"weight":23},"穆念慈":{"weight":1},"裘千丈":{"weight":1},"周伯通":{"weight":14},"黃蓉":{"weight":54},"陸冠英":{"weight":2},"簡管家":{"weight":2},"丘處機":{"weight":21},"祁志誠":{"weight":1},"沈青剛":{"weight":2},"湯祖德":{"weight":1}},"黎生":{"歐陽鋒":{"weight":2},"彭連虎":{"weight":1},"楊康":{"weight":3},"曲傻姑":{"weight":1},"完顏洪烈":{"weight":2},"孫不二":{"weight":2},"魯有腳":{"weight":5},"彭長老":{"weight":1},"簡長老":{"weight":2},"余兆興":{"weight":6},"洪七公":{"weight":13},"侯通海":{"weight":1},"梁長老":{"weight":2},"程瑤迦":{"weight":3},"黃蓉":{"weight":18},"陸冠英":{"weight":1},"歐陽克":{"weight":14},"郭靖":{"weight":17},"裘千仞":{"weight":2}},"張十五":{"楊鐵心":{"weight":8},"郭嘯天":{"weight":9}},"韓小瑩":{"都史":{"weight":6},"一燈大師":{"weight":1},"完顏洪烈":{"weight":6},"南希仁":{"weight":33},"黃藥師":{"weight":15},"譚處端":{"weight":2},"華箏":{"weight":8},"窩闊台":{"weight":2},"梅超風":{"weight":37},"尹志平":{"weight":6},"陳玄風":{"weight":18},"歐陽克":{"weight":2},"郭靖":{"weight":61},"馬鈺":{"weight":7},"博爾忽":{"weight":2},"楊康":{"weight":7},"梁子翁":{"weight":2},"武修文":{"weight":1},"王罕":{"weight":2},"孫不二":{"weight":3},"郭嘯天":{"weight":2},"柯鎮惡":{"weight":52},"段天德":{"weight":7},"彭連虎":{"weight":3},"楊過":{"weight":2},"張阿生":{"weight":28},"武敦儒":{"weight":1},"洪七公":{"weight":4},"朱聰":{"weight":71},"完顏洪熙":{"weight":1},"王處一":{"weight":4},"鐵木真":{"weight":9},"王重陽":{"weight":3},"桑昆":{"weight":5},"包惜弱":{"weight":3},"焦木大師":{"weight":4},"郝大通":{"weight":1},"劉處玄":{"weight":1},"郭芙":{"weight":1},"裘千仞":{"weight":1},"歐陽鋒":{"weight":5},"曲傻姑":{"weight":1},"楊鐵心":{"weight":4},"博爾術":{"weight":1},"韓寶駒":{"weight":50},"拖雷":{"weight":12},"穆念慈":{"weight":4},"全金發":{"weight":4},"李萍":{"weight":4},"尼摩星":{"weight":1},"周伯通":{"weight":1},"木華黎":{"weight":1},"黃蓉":{"weight":15},"陸乘風":{"weight":2},"陸冠英":{"weight":1},"丘處機":{"weight":26},"哲別":{"weight":2},"湯祖德":{"weight":1}},"孫婆婆":{"李志常":{"weight":1},"霍都":{"weight":2},"王志坦":{"weight":1},"楊過":{"weight":77},"程英":{"weight":1},"黃藥師":{"weight":1},"洪七公":{"weight":1},"李莫愁":{"weight":6},"趙志敬":{"weight":20},"尹志平":{"weight":11},"陸無雙":{"weight":2},"王處一":{"weight":1},"王重陽":{"weight":6},"林朝英":{"weight":6},"郭靖":{"weight":5},"郝大通":{"weight":20},"馬鈺":{"weight":1},"郭芙":{"weight":1},"申志凡":{"weight":1},"鹿清篤":{"weight":4},"金輪法王":{"weight":1},"歐陽鋒":{"weight":3},"洪凌波":{"weight":2},"郭襄":{"weight":1},"孫不二":{"weight":2},"公孫綠萼":{"weight":1},"周伯通":{"weight":1},"黃蓉":{"weight":2},"丘處機":{"weight":6},"小龍女":{"weight":54},"柯鎮惡":{"weight":1},"公孫止":{"weight":1}},"赤老溫":{"術赤":{"weight":4},"王罕":{"weight":5},"察合台":{"weight":4},"速不台":{"weight":2},"完顏洪烈":{"weight":3},"博爾術":{"weight":7},"拖雷":{"weight":5},"者勒米":{"weight":1},"華箏":{"weight":1},"窩闊台":{"weight":4},"李萍":{"weight":1},"完顏洪熙":{"weight":2},"木華黎":{"weight":6},"黃蓉":{"weight":1},"鐵木真":{"weight":11},"桑昆":{"weight":5},"哲別":{"weight":6},"郭靖":{"weight":9},"博爾忽":{"weight":6}},"馬青雄":{"彭連虎":{"weight":1},"楊鐵心":{"weight":1},"吳青烈":{"weight":4},"拖雷":{"weight":1},"錢青健":{"weight":4},"洪七公":{"weight":1},"華箏":{"weight":1},"侯通海":{"weight":2},"朱聰":{"weight":1},"王處一":{"weight":1},"黃蓉":{"weight":5},"陸冠英":{"weight":2},"哲別":{"weight":1},"柯鎮惡":{"weight":2},"沈青剛":{"weight":4},"郭靖":{"weight":5},"博爾忽":{"weight":1}},"童大海":{"梁長老":{"weight":3},"武修文":{"weight":1},"郭靖":{"weight":1}},"譚處端":{"完顏洪烈":{"weight":1},"南希仁":{"weight":2},"黃藥師":{"weight":15},"華箏":{"weight":2},"洪七公":{"weight":3},"梅超風":{"weight":8},"尹志平":{"weight":8},"朱聰":{"weight":2},"陳玄風":{"weight":1},"王處一":{"weight":12},"鐵木真":{"weight":1},"王重陽":{"weight":7},"郝大通":{"weight":10},"郭靖":{"weight":10},"歐陽克":{"weight":1},"馬鈺":{"weight":19},"劉處玄":{"weight":8},"裘千仞":{"weight":1},"楊康":{"weight":3},"歐陽鋒":{"weight":8},"楊鐵心":{"weight":1},"韓寶駒":{"weight":1},"孫不二":{"weight":11},"拖雷":{"weight":2},"穆念慈":{"weight":2},"耶律楚材":{"weight":1},"周伯通":{"weight":6},"黃蓉":{"weight":9},"丘處機":{"weight":18},"小龍女":{"weight":1},"柯鎮惡":{"weight":7}},"天鳴禪師":{"青靈子":{"weight":1},"趙老爵爺":{"weight":1},"郭襄":{"weight":1},"楊過":{"weight":1},"曇華大師":{"weight":1},"聾啞頭陀":{"weight":1}},"李莫愁":{"霍都":{"weight":1},"皮清玄":{"weight":1},"一燈大師":{"weight":9},"武三娘":{"weight":19},"武三通":{"weight":45},"獨孤求敗":{"weight":1},"黃藥師":{"weight":27},"耶律燕":{"weight":6},"梅超風":{"weight":4},"陸無雙":{"weight":88},"尹志平":{"weight":2},"陳玄風":{"weight":3},"朱子柳":{"weight":11},"郭靖":{"weight":37},"馬鈺":{"weight":2},"申志凡":{"weight":3},"楊康":{"weight":1},"武修文":{"weight":11},"裘千尺":{"weight":7},"馮默風":{"weight":18},"孫不二":{"weight":6},"公孫綠萼":{"weight":5},"耶律齊":{"weight":33},"小龍女":{"weight":143},"陸二娘":{"weight":3},"柯鎮惡":{"weight":14},"姬清虛":{"weight":2},"完顏萍":{"weight":17},"陸展元":{"weight":11},"曲靈風":{"weight":1},"程英":{"weight":61},"楊過":{"weight":320},"武敦儒":{"weight":9},"洪七公":{"weight":6},"趙志敬":{"weight":6},"樊一翁":{"weight":4},"王處一":{"weight":2},"王重陽":{"weight":7},"林朝英":{"weight":11},"郝大通":{"weight":3},"劉處玄":{"weight":3},"郭芙":{"weight":50},"陸立鼎":{"weight":7},"歐陽鋒":{"weight":9},"金輪法王":{"weight":39},"曲傻姑":{"weight":15},"洪凌波":{"weight":45},"郭襄":{"weight":27},"瀟湘子":{"weight":1},"尹克西":{"weight":1},"魯有腳":{"weight":2},"穆念慈":{"weight":1},"尼摩星":{"weight":3},"周伯通":{"weight":6},"黃蓉":{"weight":121},"陸乘風":{"weight":1},"丘處機":{"weight":15},"祁志誠":{"weight":1},"何沅君":{"weight":8},"公孫止":{"weight":27}},"窩闊台":{"霍都":{"weight":1},"都史":{"weight":2},"完顏洪烈":{"weight":3},"南希仁":{"weight":1},"楊過":{"weight":1},"者勒米":{"weight":2},"耶律燕":{"weight":1},"張阿生":{"weight":1},"華箏":{"weight":3},"朱聰":{"weight":2},"完顏洪熙":{"weight":1},"忽都虎":{"weight":1},"鐵木真":{"weight":20},"桑昆":{"weight":2},"郭靖":{"weight":19},"博爾忽":{"weight":4},"術赤":{"weight":9},"王罕":{"weight":1},"察合台":{"weight":8},"博爾術":{"weight":5},"韓寶駒":{"weight":2},"魯有腳":{"weight":1},"拖雷":{"weight":17},"耶律楚材":{"weight":2},"李萍":{"weight":1},"木華黎":{"weight":4},"黃蓉":{"weight":2},"耶律齊":{"weight":1},"哲別":{"weight":5},"柯鎮惡":{"weight":1},"段天德":{"weight":1}},"藍天和":{"霍都":{"weight":1},"周伯通":{"weight":2},"黃蓉":{"weight":1},"郭襄":{"weight":1},"大頭鬼":{"weight":1},"耶律齊":{"weight":8},"神雕":{"weight":1},"楊過":{"weight":1},"郭靖":{"weight":1},"郭芙":{"weight":1}},"九死生":{"聖因師太":{"weight":1},"百草仙":{"weight":2},"人廚子":{"weight":1},"韓無垢":{"weight":1},"黃蓉":{"weight":2},"郭襄":{"weight":2},"張一氓":{"weight":1},"朱子柳":{"weight":1},"郭靖":{"weight":1},"狗肉頭陀":{"weight":1},"郭芙":{"weight":1}},"陸無雙":{"完顏萍":{"weight":15},"李志常":{"weight":1},"陸展元":{"weight":4},"皮清玄":{"weight":1},"王志坦":{"weight":1},"一燈大師":{"weight":8},"楊過":{"weight":220},"武三娘":{"weight":8},"程英":{"weight":142},"武三通":{"weight":7},"耶律燕":{"weight":5},"黃藥師":{"weight":22},"洪七公":{"weight":3},"趙志敬":{"weight":2},"梅超風":{"weight":1},"瑛姑":{"weight":7},"朱子柳":{"weight":4},"郭靖":{"weight":15},"郭芙":{"weight":37},"申志凡":{"weight":4},"天竺神僧":{"weight":1},"鹿清篤":{"weight":1},"陸立鼎":{"weight":10},"裘千仞":{"weight":1},"金輪法王":{"weight":10},"歐陽鋒":{"weight":3},"武修文":{"weight":1},"裘千尺":{"weight":3},"洪凌波":{"weight":25},"曲傻姑":{"weight":9},"郭襄":{"weight":11},"馮默風":{"weight":1},"魯有腳":{"weight":1},"公孫綠萼":{"weight":6},"周伯通":{"weight":14},"黃蓉":{"weight":36},"丘處機":{"weight":1},"小龍女":{"weight":43},"神雕":{"weight":5},"耶律齊":{"weight":18},"陸二娘":{"weight":3},"柯鎮惡":{"weight":7},"何沅君":{"weight":2},"姬清虛":{"weight":4},"公孫止":{"weight":8}},"尹志平":{"李志常":{"weight":17},"霍都":{"weight":5},"完顏洪烈":{"weight":1},"王志坦":{"weight":10},"南希仁":{"weight":2},"黃藥師":{"weight":18},"華箏":{"weight":7},"梅超風":{"weight":6},"陳玄風":{"weight":1},"忽必烈":{"weight":5},"程瑤迦":{"weight":17},"張志敬":{"weight":2},"郭靖":{"weight":44},"歐陽克":{"weight":2},"馬鈺":{"weight":26},"申志凡":{"weight":1},"楊康":{"weight":6},"張志仙":{"weight":1},"孫不二":{"weight":17},"簡長老":{"weight":1},"侯通海":{"weight":5},"小龍女":{"weight":67},"柯鎮惡":{"weight":10},"段天德":{"weight":2},"彭連虎":{"weight":2},"楊過":{"weight":47},"張阿生":{"weight":2},"洪七公":{"weight":6},"趙志敬":{"weight":108},"朱聰":{"weight":7},"王處一":{"weight":22},"鐵木真":{"weight":6},"桑昆":{"weight":1},"王重陽":{"weight":7},"林朝英":{"weight":1},"郝大通":{"weight":17},"劉處玄":{"weight":8},"鹿清篤":{"weight":7},"郭芙":{"weight":1},"裘千仞":{"weight":2},"歐陽鋒":{"weight":7},"金輪法王":{"weight":23},"達爾巴":{"weight":3},"郭襄":{"weight":1},"瀟湘子":{"weight":3},"楊鐵心":{"weight":2},"博爾術":{"weight":1},"尹克西":{"weight":2},"韓寶駒":{"weight":4},"拖雷":{"weight":4},"穆念慈":{"weight":3},"彭長老":{"weight":1},"李萍":{"weight":1},"尼摩星":{"weight":6},"周伯通":{"weight":7},"黃蓉":{"weight":23},"陸乘風":{"weight":1},"陸冠英":{"weight":19},"丘處機":{"weight":46},"哲別":{"weight":1},"祁志誠":{"weight":12}},"陳玄風":{"彭連虎":{"weight":7},"柯辟邪":{"weight":2},"黃裳":{"weight":2},"都史":{"weight":2},"一燈大師":{"weight":2},"完顏洪烈":{"weight":4},"曲靈風":{"weight":2},"南希仁":{"weight":11},"程英":{"weight":1},"楊過":{"weight":1},"枯木大師":{"weight":1},"張阿生":{"weight":12},"黃藥師":{"weight":24},"華箏":{"weight":1},"洪七公":{"weight":6},"梅超風":{"weight":59},"朱聰":{"weight":21},"王處一":{"weight":1},"鐵木真":{"weight":2},"桑昆":{"weight":2},"王重陽":{"weight":3},"瑛姑":{"weight":2},"郝大通":{"weight":1},"郭靖":{"weight":43},"歐陽克":{"weight":5},"馬鈺":{"weight":4},"劉處玄":{"weight":1},"博爾忽":{"weight":1},"裘千仞":{"weight":5},"楊康":{"weight":7},"歐陽鋒":{"weight":7},"梁子翁":{"weight":4},"楊鐵心":{"weight":1},"馮默風":{"weight":2},"韓寶駒":{"weight":18},"孫不二":{"weight":1},"黃夫人":{"weight":1},"靈智上人":{"weight":2},"拖雷":{"weight":1},"郭嘯天":{"weight":1},"全金發":{"weight":1},"侯通海":{"weight":2},"周伯通":{"weight":10},"黃蓉":{"weight":25},"陸乘風":{"weight":7},"陸冠英":{"weight":4},"丘處機":{"weight":9},"柯鎮惡":{"weight":19}},"忽必烈":{"王志坦":{"weight":1},"楊過":{"weight":39},"武敦儒":{"weight":2},"黃藥師":{"weight":1},"趙志敬":{"weight":4},"樊一翁":{"weight":1},"鐵木真":{"weight":7},"馬光佐":{"weight":7},"朱子柳":{"weight":1},"呂文德":{"weight":3},"郭靖":{"weight":44},"郭芙":{"weight":4},"金輪法王":{"weight":52},"武修文":{"weight":4},"郭襄":{"weight":2},"瀟湘子":{"weight":14},"尹克西":{"weight":7},"馮默風":{"weight":1},"拖雷":{"weight":5},"尼摩星":{"weight":12},"周伯通":{"weight":10},"黃蓉":{"weight":4},"大頭鬼":{"weight":1},"丘處機":{"weight":1},"小龍女":{"weight":12},"祁志誠":{"weight":1},"哲別":{"weight":1},"柯鎮惡":{"weight":1},"蒙哥":{"weight":3}},"朱子柳":{"完顏萍":{"weight":4},"李志常":{"weight":1},"聖因師太":{"weight":3},"霍都":{"weight":39},"人廚子":{"weight":1},"一燈大師":{"weight":13},"楊過":{"weight":58},"程英":{"weight":6},"武三通":{"weight":24},"耶律燕":{"weight":2},"武敦儒":{"weight":4},"黃藥師":{"weight":6},"洪七公":{"weight":3},"無常鬼":{"weight":1},"王處一":{"weight":1},"程瑤迦":{"weight":1},"王重陽":{"weight":1},"點蒼漁隱":{"weight":4},"林朝英":{"weight":1},"呂文德":{"weight":1},"郭靖":{"weight":32},"郝大通":{"weight":2},"馬鈺":{"weight":1},"郭芙":{"weight":22},"天竺神僧":{"weight":2},"裘千仞":{"weight":6},"金輪法王":{"weight":14},"歐陽鋒":{"weight":2},"達爾巴":{"weight":6},"武修文":{"weight":2},"百草仙":{"weight":2},"裘千尺":{"weight":7},"瀟湘子":{"weight":4},"郭襄":{"weight":11},"張一氓":{"weight":3},"魯有腳":{"weight":5},"彭長老":{"weight":1},"公孫綠萼":{"weight":2},"尼摩星":{"weight":4},"周伯通":{"weight":5},"黃蓉":{"weight":44},"陸冠英":{"weight":1},"丘處機":{"weight":1},"耶律齊":{"weight":6},"小龍女":{"weight":30},"公孫止":{"weight":9}},"歐陽克":{"彭連虎":{"weight":29},"完顏洪烈":{"weight":12},"一燈大師":{"weight":9},"南希仁":{"weight":3},"楊過":{"weight":3},"黃藥師":{"weight":52},"洪七公":{"weight":97},"華箏":{"weight":2},"無常鬼":{"weight":1},"梅超風":{"weight":20},"朱聰":{"weight":4},"王處一":{"weight":10},"程瑤迦":{"weight":17},"瑛姑":{"weight":2},"王重陽":{"weight":6},"郭靖":{"weight":127},"馬鈺":{"weight":5},"裘千仞":{"weight":2},"楊康":{"weight":37},"歐陽鋒":{"weight":94},"梁子翁":{"weight":21},"曲傻姑":{"weight":5},"楊鐵心":{"weight":6},"博爾術":{"weight":1},"孫不二":{"weight":3},"韓寶駒":{"weight":4},"靈智上人":{"weight":6},"拖雷":{"weight":3},"黃夫人":{"weight":1},"魯有腳":{"weight":3},"穆念慈":{"weight":26},"余兆興":{"weight":2},"侯通海":{"weight":18},"梁長老":{"weight":1},"周伯通":{"weight":16},"黃蓉":{"weight":154},"陸冠英":{"weight":14},"丘處機":{"weight":9},"簡管家":{"weight":1},"哲別":{"weight":1},"柯鎮惡":{"weight":5},"段天德":{"weight":1},"湯祖德":{"weight":1}},"郭靖":{"張志敬":{"weight":1},"馬鈺":{"weight":85},"博爾忽":{"weight":18},"梁子翁":{"weight":67},"裘千尺":{"weight":14},"王罕":{"weight":17},"公孫綠萼":{"weight":2},"梁長老":{"weight":6},"莫圖根":{"weight":1},"神雕":{"weight":16},"耶律齊":{"weight":17},"完顏萍":{"weight":2},"史彌遠":{"weight":2},"陸展元":{"weight":2},"曲靈風":{"weight":7},"楊過":{"weight":489},"程英":{"weight":7},"枯木大師":{"weight":3},"者勒米":{"weight":4},"無常鬼":{"weight":3},"朱聰":{"weight":104},"摩訶末":{"weight":6},"王彥章":{"weight":1},"郝大通":{"weight":28},"曇華大師":{"weight":1},"劉處玄":{"weight":10},"郭芙":{"weight":125},"術赤":{"weight":18},"史伯威":{"weight":4},"趙老爵爺":{"weight":3},"百草仙":{"weight":4},"上官劍南":{"weight":4},"察合台":{"weight":16},"曲傻姑":{"weight":30},"楊鐵心":{"weight":57},"張一氓":{"weight":3},"吳青烈":{"weight":5},"魯有腳":{"weight":65},"穆念慈":{"weight":66},"全金發":{"weight":3},"李萍":{"weight":17},"尼摩星":{"weight":38},"周伯通":{"weight":208},"木華黎":{"weight":7},"黃蓉":{"weight":1155},"大頭鬼":{"weight":4},"祁志誠":{"weight":1},"哲別":{"weight":41},"郭破虜":{"weight":8},"沈青剛":{"weight":6},"蒙哥":{"weight":4},"何沅君":{"weight":2},"湯祖德":{"weight":4},"李志常":{"weight":4},"聖因師太":{"weight":4},"霍都":{"weight":43},"黃裳":{"weight":7},"都史":{"weight":16},"王志坦":{"weight":1},"一燈大師":{"weight":95},"完顏洪烈":{"weight":96},"南希仁":{"weight":35},"武三娘":{"weight":3},"武三通":{"weight":11},"獨孤求敗":{"weight":1},"黃藥師":{"weight":311},"耶律燕":{"weight":2},"華箏":{"weight":78},"梅超風":{"weight":131},"程瑤迦":{"weight":21},"馬光佐":{"weight":10},"呂文德":{"weight":26},"楊康":{"weight":194},"武修文":{"weight":27},"張志仙":{"weight":1},"孫不二":{"weight":31},"馮默風":{"weight":9},"郭嘯天":{"weight":9},"黃夫人":{"weight":5},"簡長老":{"weight":17},"余兆興":{"weight":3},"耶律楚材":{"weight":2},"侯通海":{"weight":46},"喬寨主":{"weight":1},"石彥明":{"weight":1},"小龍女":{"weight":121},"柯鎮惡":{"weight":117},"段天德":{"weight":9},"彭連虎":{"weight":59},"人廚子":{"weight":2},"速不台":{"weight":3},"張阿生":{"weight":18},"武敦儒":{"weight":11},"錢青健":{"weight":8},"洪七公":{"weight":296},"趙志敬":{"weight":37},"樊一翁":{"weight":6},"王處一":{"weight":70},"忽都虎":{"weight":2},"完顏洪熙":{"weight":6},"鐵木真":{"weight":128},"瑛姑":{"weight":44},"桑昆":{"weight":21},"王重陽":{"weight":39},"包惜弱":{"weight":10},"點蒼漁隱":{"weight":4},"林朝英":{"weight":1},"焦木大師":{"weight":1},"裘千仞":{"weight":94},"金輪法王":{"weight":135},"歐陽鋒":{"weight":325},"達爾巴":{"weight":18},"瀟湘子":{"weight":43},"郭襄":{"weight":68},"博爾術":{"weight":15},"尹克西":{"weight":16},"韓寶駒":{"weight":61},"狗肉頭陀":{"weight":1},"拖雷":{"weight":87},"靈智上人":{"weight":33},"彭長老":{"weight":14},"聾啞頭陀":{"weight":3},"裘千丈":{"weight":12},"韓無垢":{"weight":3},"陸乘風":{"weight":30},"陸冠英":{"weight":54},"簡管家":{"weight":8},"丘處機":{"weight":158},"公孫止":{"weight":7}},"張志敬":{"李志常":{"weight":2},"彭連虎":{"weight":1},"張志仙":{"weight":1},"王志坦":{"weight":2},"孫不二":{"weight":1},"趙志敬":{"weight":2},"王處一":{"weight":1},"黃蓉":{"weight":1},"丘處機":{"weight":1},"祁志誠":{"weight":2},"郝大通":{"weight":1},"馬鈺":{"weight":1},"劉處玄":{"weight":1},"裘千仞":{"weight":1}},"馬鈺":{"李志常":{"weight":1},"霍都":{"weight":1},"都史":{"weight":1},"完顏洪烈":{"weight":4},"一燈大師":{"weight":5},"王志坦":{"weight":1},"南希仁":{"weight":1},"黃藥師":{"weight":35},"華箏":{"weight":12},"梅超風":{"weight":30},"程瑤迦":{"weight":1},"楊康":{"weight":17},"梁子翁":{"weight":3},"王罕":{"weight":1},"張志仙":{"weight":1},"孫不二":{"weight":21},"黃夫人":{"weight":1},"簡長老":{"weight":3},"耶律楚材":{"weight":1},"侯通海":{"weight":3},"耶律齊":{"weight":1},"小龍女":{"weight":4},"柯鎮惡":{"weight":22},"段天德":{"weight":1},"彭連虎":{"weight":10},"楊過":{"weight":13},"張阿生":{"weight":1},"錢青健":{"weight":1},"洪七公":{"weight":19},"趙志敬":{"weight":8},"朱聰":{"weight":18},"王處一":{"weight":54},"鐵木真":{"weight":3},"桑昆":{"weight":4},"王重陽":{"weight":15},"瑛姑":{"weight":1},"包惜弱":{"weight":2},"郝大通":{"weight":20},"劉處玄":{"weight":18},"陸立鼎":{"weight":1},"裘千仞":{"weight":8},"歐陽鋒":{"weight":21},"金輪法王":{"weight":2},"楊鐵心":{"weight":8},"博爾術":{"weight":1},"韓寶駒":{"weight":3},"靈智上人":{"weight":2},"魯有腳":{"weight":2},"拖雷":{"weight":4},"穆念慈":{"weight":9},"彭長老":{"weight":2},"全金發":{"weight":1},"裘千丈":{"weight":1},"周伯通":{"weight":25},"黃蓉":{"weight":41},"陸乘風":{"weight":3},"陸冠英":{"weight":2},"丘處機":{"weight":83},"祁志誠":{"weight":1},"哲別":{"weight":1},"湯祖德":{"weight":1},"公孫止":{"weight":1}},"博爾忽":{"速不台":{"weight":1},"都史":{"weight":3},"完顏洪烈":{"weight":8},"者勒米":{"weight":1},"錢青健":{"weight":1},"華箏":{"weight":3},"梅超風":{"weight":1},"朱聰":{"weight":2},"完顏洪熙":{"weight":3},"摩訶末":{"weight":1},"鐵木真":{"weight":14},"桑昆":{"weight":5},"術赤":{"weight":4},"王罕":{"weight":4},"察合台":{"weight":2},"吳青烈":{"weight":1},"博爾術":{"weight":5},"韓寶駒":{"weight":1},"拖雷":{"weight":13},"李萍":{"weight":1},"木華黎":{"weight":6},"黃蓉":{"weight":3},"陸冠英":{"weight":1},"哲別":{"weight":9},"柯鎮惡":{"weight":1},"沈青剛":{"weight":1}},"姜文":{"蓋運聰":{"weight":1},"楊鐵心":{"weight":1},"完顏洪烈":{"weight":1},"包惜弱":{"weight":1}},"梁子翁":{"彭連虎":{"weight":45},"完顏洪烈":{"weight":26},"南希仁":{"weight":4},"黃藥師":{"weight":9},"錢青健":{"weight":1},"洪七公":{"weight":22},"無常鬼":{"weight":1},"梅超風":{"weight":15},"朱聰":{"weight":5},"王處一":{"weight":10},"鐵木真":{"weight":1},"包惜弱":{"weight":1},"裘千仞":{"weight":2},"楊康":{"weight":25},"歐陽鋒":{"weight":16},"曲傻姑":{"weight":9},"楊鐵心":{"weight":6},"韓寶駒":{"weight":3},"靈智上人":{"weight":20},"侯通海":{"weight":23},"周伯通":{"weight":7},"黃蓉":{"weight":55},"丘處機":{"weight":9},"簡管家":{"weight":4},"柯鎮惡":{"weight":10},"湯祖德":{"weight":2}},"裘千尺":{"完顏萍":{"weight":4},"一燈大師":{"weight":8},"楊過":{"weight":113},"程英":{"weight":2},"武三通":{"weight":9},"耶律燕":{"weight":1},"樊一翁":{"weight":6},"瑛姑":{"weight":1},"馬光佐":{"weight":3},"點蒼漁隱":{"weight":1},"郭芙":{"weight":11},"天竺神僧":{"weight":4},"裘千仞":{"weight":30},"楊康":{"weight":1},"金輪法王":{"weight":12},"瀟湘子":{"weight":2},"郭襄":{"weight":2},"尹克西":{"weight":4},"穆念慈":{"weight":1},"彭長老":{"weight":1},"公孫綠萼":{"weight":75},"裘千丈":{"weight":6},"周伯通":{"weight":2},"黃蓉":{"weight":50},"耶律齊":{"weight":6},"小龍女":{"weight":34},"公孫止":{"weight":73}},"王罕":{"術赤":{"weight":4},"速不台":{"weight":1},"察合台":{"weight":3},"都史":{"weight":12},"完顏洪烈":{"weight":13},"南希仁":{"weight":1},"博爾術":{"weight":4},"韓寶駒":{"weight":1},"者勒米":{"weight":3},"張阿生":{"weight":2},"拖雷":{"weight":9},"華箏":{"weight":7},"李萍":{"weight":1},"梅超風":{"weight":1},"朱聰":{"weight":3},"木華黎":{"weight":6},"完顏洪熙":{"weight":13},"鐵木真":{"weight":34},"丘處機":{"weight":2},"桑昆":{"weight":24},"哲別":{"weight":10},"柯鎮惡":{"weight":1}},"史孟捷":{"史季強":{"weight":10},"史伯威":{"weight":6},"吊死鬼":{"weight":2},"郭襄":{"weight":8},"俏鬼":{"weight":2},"楊過":{"weight":10},"催命鬼":{"weight":1},"喪門鬼":{"weight":2},"樊一翁":{"weight":5},"大頭鬼":{"weight":6},"耶律齊":{"weight":1},"神雕":{"weight":5},"笑臉鬼":{"weight":2},"史叔剛":{"weight":4},"郭芙":{"weight":11},"史仲猛":{"weight":7}},"梁長老":{"金輪法王":{"weight":1},"楊康":{"weight":4},"達爾巴":{"weight":1},"霍都":{"weight":7},"武修文":{"weight":1},"郭襄":{"weight":1},"楊過":{"weight":1},"黃藥師":{"weight":4},"耶律燕":{"weight":1},"魯有腳":{"weight":8},"彭長老":{"weight":4},"簡長老":{"weight":5},"余兆興":{"weight":1},"洪七公":{"weight":2},"周伯通":{"weight":1},"程瑤迦":{"weight":1},"黃蓉":{"weight":13},"耶律齊":{"weight":8},"郭芙":{"weight":4},"裘千仞":{"weight":2}},"公孫綠萼":{"金輪法王":{"weight":2},"歐陽鋒":{"weight":1},"完顏萍":{"weight":1},"一燈大師":{"weight":1},"尹克西":{"weight":1},"楊過":{"weight":174},"程英":{"weight":6},"武三通":{"weight":1},"黃藥師":{"weight":2},"裘千丈":{"weight":1},"樊一翁":{"weight":10},"周伯通":{"weight":5},"黃蓉":{"weight":12},"神雕":{"weight":1},"耶律齊":{"weight":1},"小龍女":{"weight":40},"馬光佐":{"weight":1},"點蒼漁隱":{"weight":1},"天竺神僧":{"weight":1},"公孫止":{"weight":48},"裘千仞":{"weight":6}},"催命鬼":{"史季強":{"weight":1},"吊死鬼":{"weight":1},"喪門鬼":{"weight":2},"討債鬼":{"weight":1},"俏鬼":{"weight":1},"大頭鬼":{"weight":1},"史仲猛":{"weight":2}},"莫圖根":{"察合台":{"weight":1},"黃蓉":{"weight":1},"鐵木真":{"weight":1},"完顏洪烈":{"weight":1},"魯有腳":{"weight":1}},"耶律齊":{"完顏萍":{"weight":34},"霍都":{"weight":19},"一燈大師":{"weight":7},"程英":{"weight":9},"楊過":{"weight":60},"武三通":{"weight":25},"耶律燕":{"weight":18},"武敦儒":{"weight":6},"黃藥師":{"weight":4},"青靈子":{"weight":1},"鐵木真":{"weight":1},"王重陽":{"weight":1},"瑛姑":{"weight":1},"呂文德":{"weight":2},"郝大通":{"weight":1},"劉處玄":{"weight":2},"郭芙":{"weight":74},"裘千仞":{"weight":6},"金輪法王":{"weight":1},"達爾巴":{"weight":2},"武修文":{"weight":5},"洪凌波":{"weight":3},"郭襄":{"weight":17},"孫不二":{"weight":2},"魯有腳":{"weight":5},"耶律楚材":{"weight":4},"尼摩星":{"weight":4},"周伯通":{"weight":10},"黃蓉":{"weight":40},"丘處機":{"weight":3},"大頭鬼":{"weight":2},"神雕":{"weight":4},"小龍女":{"weight":15},"郭破虜":{"weight":3},"史叔剛":{"weight":1},"蒙哥":{"weight":2},"公孫止":{"weight":9}},"神雕":{"史彌遠":{"weight":1},"聖因師太":{"weight":1},"霍都":{"weight":1},"人廚子":{"weight":1},"煞神鬼":{"weight":3},"一燈大師":{"weight":2},"程英":{"weight":1},"楊過":{"weight":216},"獨孤求敗":{"weight":13},"武敦儒":{"weight":1},"黃藥師":{"weight":6},"青靈子":{"weight":4},"洪七公":{"weight":1},"樊一翁":{"weight":9},"鐵木真":{"weight":1},"王重陽":{"weight":1},"瑛姑":{"weight":1},"郭芙":{"weight":14},"史仲猛":{"weight":4},"裘千仞":{"weight":2},"金輪法王":{"weight":3},"史季強":{"weight":3},"歐陽鋒":{"weight":1},"史伯威":{"weight":10},"達爾巴":{"weight":2},"武修文":{"weight":2},"百草仙":{"weight":1},"郭襄":{"weight":72},"張一氓":{"weight":1},"周伯通":{"weight":5},"黃蓉":{"weight":16},"大頭鬼":{"weight":14},"小龍女":{"weight":17},"史叔剛":{"weight":4},"蒙哥":{"weight":1},"公孫止":{"weight":1}},"史叔剛":{"青靈子":{"weight":1},"史季強":{"weight":7},"達爾巴":{"weight":1},"史伯威":{"weight":3},"吊死鬼":{"weight":4},"霍都":{"weight":1},"樊一翁":{"weight":3},"郭襄":{"weight":7},"楊過":{"weight":9},"笑臉鬼":{"weight":5},"史仲猛":{"weight":2}},"完顏萍":{"歐陽鋒":{"weight":1},"金輪法王":{"weight":1},"武修文":{"weight":9},"一燈大師":{"weight":2},"程英":{"weight":2},"楊過":{"weight":56},"武三通":{"weight":8},"武敦儒":{"weight":9},"魯有腳":{"weight":1},"黃藥師":{"weight":2},"耶律燕":{"weight":21},"耶律楚材":{"weight":4},"洪七公":{"weight":1},"周伯通":{"weight":1},"黃蓉":{"weight":11},"小龍女":{"weight":13},"公孫止":{"weight":12},"郭芙":{"weight":20},"裘千仞":{"weight":1}},"史彌遠":{"楊康":{"weight":3},"華箏":{"weight":1},"鐵木真":{"weight":1},"楊過":{"weight":1},"拖雷":{"weight":2},"穆念慈":{"weight":3}},"陸展元":{"黃蓉":{"weight":2},"陸乘風":{"weight":1},"一燈大師":{"weight":1},"小龍女":{"weight":2},"程英":{"weight":1},"楊過":{"weight":2},"武三娘":{"weight":2},"武三通":{"weight":5},"陸二娘":{"weight":2},"何沅君":{"weight":8},"黃藥師":{"weight":1},"陸立鼎":{"weight":4}},"曲靈風":{"歐陽鋒":{"weight":1},"上官劍南":{"weight":1},"曲傻姑":{"weight":7},"程英":{"weight":1},"馮默風":{"weight":2},"黃藥師":{"weight":9},"洪七公":{"weight":1},"梅超風":{"weight":3},"周伯通":{"weight":3},"黃蓉":{"weight":11},"陸乘風":{"weight":3},"小龍女":{"weight":1},"裘千仞":{"weight":1}},"俏鬼":{"史季強":{"weight":2},"史伯威":{"weight":1},"吊死鬼":{"weight":2},"喪門鬼":{"weight":1},"樊一翁":{"weight":2},"大頭鬼":{"weight":3},"笑臉鬼":{"weight":1},"史仲猛":{"weight":1}},"程英":{"一燈大師":{"weight":8},"武三娘":{"weight":7},"楊過":{"weight":111},"武三通":{"weight":10},"耶律燕":{"weight":1},"黃藥師":{"weight":28},"洪七公":{"weight":1},"梅超風":{"weight":1},"瑛姑":{"weight":7},"天竺神僧":{"weight":1},"郭芙":{"weight":25},"陸立鼎":{"weight":6},"裘千仞":{"weight":2},"歐陽鋒":{"weight":1},"金輪法王":{"weight":9},"武修文":{"weight":1},"洪凌波":{"weight":5},"曲傻姑":{"weight":20},"郭襄":{"weight":11},"瀟湘子":{"weight":1},"馮默風":{"weight":6},"周伯通":{"weight":12},"黃蓉":{"weight":38},"陸乘風":{"weight":1},"小龍女":{"weight":30},"柯鎮惡":{"weight":5},"陸二娘":{"weight":2},"何沅君":{"weight":5},"公孫止":{"weight":6}},"楊過":{"聖因師太":{"weight":1},"霍都":{"weight":81},"皮清玄":{"weight":8},"完顏洪烈":{"weight":3},"一燈大師":{"weight":58},"南希仁":{"weight":1},"武三娘":{"weight":1},"武三通":{"weight":72},"獨孤求敗":{"weight":11},"黃藥師":{"weight":108},"耶律燕":{"weight":12},"華箏":{"weight":2},"青靈子":{"weight":3},"梅超風":{"weight":3},"程瑤迦":{"weight":1},"馬光佐":{"weight":41},"呂文德":{"weight":5},"申志凡":{"weight":8},"史仲猛":{"weight":8},"天竺神僧":{"weight":7},"楊康":{"weight":30},"武修文":{"weight":71},"馮默風":{"weight":14},"孫不二":{"weight":23},"郭嘯天":{"weight":3},"耶律楚材":{"weight":7},"小龍女":{"weight":1074},"柯鎮惡":{"weight":42},"姬清虛":{"weight":9},"彭連虎":{"weight":3},"人廚子":{"weight":1},"煞神鬼":{"weight":5},"武敦儒":{"weight":50},"洪七公":{"weight":81},"趙志敬":{"weight":118},"樊一翁":{"weight":63},"朱聰":{"weight":4},"王處一":{"weight":16},"鐵木真":{"weight":6},"瑛姑":{"weight":31},"王重陽":{"weight":51},"點蒼漁隱":{"weight":7},"包惜弱":{"weight":1},"林朝英":{"weight":53},"郝大通":{"weight":34},"鹿清篤":{"weight":25},"劉處玄":{"weight":5},"郭芙":{"weight":289},"陸立鼎":{"weight":1},"裘千仞":{"weight":47},"歐陽鋒":{"weight":98},"金輪法王":{"weight":331},"史季強":{"weight":6},"史伯威":{"weight":13},"達爾巴":{"weight":67},"百草仙":{"weight":1},"曲傻姑":{"weight":38},"洪凌波":{"weight":51},"楊鐵心":{"weight":7},"郭襄":{"weight":297},"瀟湘子":{"weight":77},"張一氓":{"weight":1},"尹克西":{"weight":59},"韓寶駒":{"weight":1},"魯有腳":{"weight":24},"拖雷":{"weight":3},"穆念慈":{"weight":9},"彭長老":{"weight":16},"全金發":{"weight":1},"裘千丈":{"weight":2},"周伯通":{"weight":155},"尼摩星":{"weight":50},"黃蓉":{"weight":495},"陸冠英":{"weight":1},"大頭鬼":{"weight":16},"丘處機":{"weight":49},"郭破虜":{"weight":3},"蒙哥":{"weight":8},"何沅君":{"weight":2},"公孫止":{"weight":174}},"枯木大師":{"楊康":{"weight":1},"梅超風":{"weight":1},"朱聰":{"weight":1},"黃蓉":{"weight":2},"陸冠英":{"weight":4},"陸乘風":{"weight":2},"丘處機":{"weight":1},"段天德":{"weight":1},"黃藥師":{"weight":1},"裘千仞":{"weight":1}},"者勒米":{"術赤":{"weight":1},"忽都虎":{"weight":2},"完顏洪熙":{"weight":2},"察合台":{"weight":1},"速不台":{"weight":1},"木華黎":{"weight":1},"鐵木真":{"weight":6},"完顏洪烈":{"weight":1},"博爾術":{"weight":1},"桑昆":{"weight":2},"哲別":{"weight":4},"拖雷":{"weight":1}},"無常鬼":{"彭連虎":{"weight":1},"歐陽鋒":{"weight":1},"楊康":{"weight":1},"聖因師太":{"weight":1},"人廚子":{"weight":1},"百草仙":{"weight":1},"郭襄":{"weight":2},"張一氓":{"weight":1},"完顏洪烈":{"weight":1},"靈智上人":{"weight":1},"侯通海":{"weight":1},"周伯通":{"weight":2},"黃蓉":{"weight":2},"大頭鬼":{"weight":1},"郭芙":{"weight":2}},"朱聰":{"柯辟邪":{"weight":1},"都史":{"weight":7},"完顏洪烈":{"weight":12},"一燈大師":{"weight":1},"南希仁":{"weight":44},"黃藥師":{"weight":27},"華箏":{"weight":13},"梅超風":{"weight":52},"楊康":{"weight":21},"孫不二":{"weight":3},"郭嘯天":{"weight":4},"侯通海":{"weight":3},"小龍女":{"weight":1},"柯鎮惡":{"weight":77},"段天德":{"weight":9},"彭連虎":{"weight":15},"張阿生":{"weight":34},"錢青健":{"weight":1},"洪七公":{"weight":8},"完顏洪熙":{"weight":1},"王處一":{"weight":8},"鐵木真":{"weight":10},"瑛姑":{"weight":1},"桑昆":{"weight":6},"王重陽":{"weight":4},"包惜弱":{"weight":5},"郝大通":{"weight":1},"焦木大師":{"weight":7},"劉處玄":{"weight":1},"裘千仞":{"weight":13},"歐陽鋒":{"weight":12},"曲傻姑":{"weight":3},"楊鐵心":{"weight":9},"吳青烈":{"weight":1},"博爾術":{"weight":1},"韓寶駒":{"weight":65},"靈智上人":{"weight":1},"拖雷":{"weight":14},"穆念慈":{"weight":6},"彭長老":{"weight":1},"全金發":{"weight":4},"李萍":{"weight":4},"周伯通":{"weight":4},"木華黎":{"weight":1},"黃蓉":{"weight":46},"陸冠英":{"weight":5},"陸乘風":{"weight":7},"丘處機":{"weight":50},"哲別":{"weight":2},"沈青剛":{"weight":1},"湯祖德":{"weight":1}},"摩訶末":{"術赤":{"weight":1},"歐陽鋒":{"weight":1},"周伯通":{"weight":1},"速不台":{"weight":1},"黃蓉":{"weight":1},"鐵木真":{"weight":5},"完顏洪烈":{"weight":3},"桑昆":{"weight":1},"哲別":{"weight":1},"魯有腳":{"weight":1},"裘千仞":{"weight":1}},"郝大通":{"李志常":{"weight":2},"彭連虎":{"weight":1},"霍都":{"weight":9},"一燈大師":{"weight":2},"完顏洪烈":{"weight":1},"王志坦":{"weight":1},"南希仁":{"weight":1},"武敦儒":{"weight":1},"黃藥師":{"weight":11},"洪七公":{"weight":4},"華箏":{"weight":2},"趙志敬":{"weight":16},"梅超風":{"weight":6},"王處一":{"weight":22},"王重陽":{"weight":11},"點蒼漁隱":{"weight":1},"林朝英":{"weight":2},"劉處玄":{"weight":17},"郭芙":{"weight":2},"裘千仞":{"weight":1},"金輪法王":{"weight":5},"楊康":{"weight":2},"歐陽鋒":{"weight":4},"達爾巴":{"weight":4},"武修文":{"weight":1},"楊鐵心":{"weight":1},"張志仙":{"weight":1},"孫不二":{"weight":25},"靈智上人":{"weight":1},"拖雷":{"weight":1},"穆念慈":{"weight":2},"周伯通":{"weight":14},"黃蓉":{"weight":20},"陸冠英":{"weight":3},"丘處機":{"weight":34},"小龍女":{"weight":32},"祁志誠":{"weight":1},"柯鎮惡":{"weight":6},"公孫止":{"weight":2}},"王彥章":{"楊康":{"weight":1},"歐陽鋒":{"weight":1},"黃蓉":{"weight":1},"柯鎮惡":{"weight":3}},"郭芙":{"李志常":{"weight":1},"聖因師太":{"weight":1},"霍都":{"weight":24},"人廚子":{"weight":1},"一燈大師":{"weight":6},"武三娘":{"weight":2},"武三通":{"weight":38},"武敦儒":{"weight":36},"黃藥師":{"weight":19},"耶律燕":{"weight":17},"洪七公":{"weight":6},"趙志敬":{"weight":3},"樊一翁":{"weight":1},"瑛姑":{"weight":1},"呂文德":{"weight":3},"林朝英":{"weight":1},"史仲猛":{"weight":1},"裘千仞":{"weight":9},"歐陽鋒":{"weight":5},"金輪法王":{"weight":33},"楊康":{"weight":2},"史季強":{"weight":4},"達爾巴":{"weight":9},"武修文":{"weight":49},"百草仙":{"weight":2},"曲傻姑":{"weight":1},"洪凌波":{"weight":2},"楊鐵心":{"weight":1},"郭襄":{"weight":83},"瀟湘子":{"weight":2},"張一氓":{"weight":1},"韓寶駒":{"weight":1},"郭嘯天":{"weight":1},"魯有腳":{"weight":22},"穆念慈":{"weight":1},"周伯通":{"weight":8},"尼摩星":{"weight":18},"黃蓉":{"weight":218},"大頭鬼":{"weight":7},"丘處機":{"weight":3},"小龍女":{"weight":76},"柯鎮惡":{"weight":14},"郭破虜":{"weight":11},"公孫止":{"weight":23}},"劉處玄":{"李志常":{"weight":2},"彭連虎":{"weight":1},"一燈大師":{"weight":1},"王志坦":{"weight":1},"南希仁":{"weight":1},"黃藥師":{"weight":9},"華箏":{"weight":1},"洪七公":{"weight":4},"趙志敬":{"weight":4},"梅超風":{"weight":7},"王處一":{"weight":17},"王重陽":{"weight":4},"鹿清篤":{"weight":1},"裘千仞":{"weight":4},"陸立鼎":{"weight":1},"楊康":{"weight":1},"歐陽鋒":{"weight":3},"張志仙":{"weight":1},"孫不二":{"weight":17},"拖雷":{"weight":1},"穆念慈":{"weight":1},"尼摩星":{"weight":1},"周伯通":{"weight":10},"黃蓉":{"weight":9},"丘處機":{"weight":26},"小龍女":{"weight":9},"祁志誠":{"weight":1},"柯鎮惡":{"weight":6}},"鹿清篤":{"金輪法王":{"weight":2},"李志常":{"weight":2},"武修文":{"weight":1},"瀟湘子":{"weight":3},"王志坦":{"weight":2},"尹克西":{"weight":2},"趙志敬":{"weight":14},"尼摩星":{"weight":3},"王處一":{"weight":3},"丘處機":{"weight":3},"王重陽":{"weight":1},"小龍女":{"weight":7},"公孫止":{"weight":1},"申志凡":{"weight":1}},"曇華大師":{"青靈子":{"weight":1},"金輪法王":{"weight":1},"趙老爵爺":{"weight":2},"達爾巴":{"weight":1},"郭襄":{"weight":1},"黃蓉":{"weight":1},"聾啞頭陀":{"weight":1}},"陸立鼎":{"洪凌波":{"weight":1},"一燈大師":{"weight":1},"丘處機":{"weight":1},"武三娘":{"weight":9},"武三通":{"weight":4},"孫不二":{"weight":1},"陸二娘":{"weight":12},"何沅君":{"weight":2}},"術赤":{"歐陽鋒":{"weight":1},"霍都":{"weight":1},"察合台":{"weight":14},"都史":{"weight":2},"完顏洪烈":{"weight":4},"博爾術":{"weight":7},"魯有腳":{"weight":2},"拖雷":{"weight":10},"華箏":{"weight":3},"木華黎":{"weight":4},"完顏洪熙":{"weight":1},"鐵木真":{"weight":17},"黃蓉":{"weight":2},"丘處機":{"weight":1},"桑昆":{"weight":4},"哲別":{"weight":6}},"史伯威":{"史季強":{"weight":6},"吊死鬼":{"weight":1},"樊一翁":{"weight":11},"鐵木真":{"weight":1},"郭襄":{"weight":4},"黃蓉":{"weight":4},"大頭鬼":{"weight":1},"笑臉鬼":{"weight":1},"蒙哥":{"weight":1},"史仲猛":{"weight":5}},"趙老爵爺":{"青靈子":{"weight":1},"金輪法王":{"weight":1},"達爾巴":{"weight":1},"尼摩星":{"weight":1},"郭襄":{"weight":2},"黃蓉":{"weight":4},"聾啞頭陀":{"weight":5}},"百草仙":{"聖因師太":{"weight":4},"人廚子":{"weight":3},"樊一翁":{"weight":1},"韓無垢":{"weight":2},"黃蓉":{"weight":7},"郭襄":{"weight":6},"張一氓":{"weight":3},"狗肉頭陀":{"weight":1},"聾啞頭陀":{"weight":1}},"上官劍南":{"洪七公":{"weight":1},"周伯通":{"weight":1},"黃蓉":{"weight":4},"一燈大師":{"weight":1},"瑛姑":{"weight":2},"裘千仞":{"weight":2}},"曲傻姑":{"彭連虎":{"weight":5},"一燈大師":{"weight":1},"完顏洪烈":{"weight":4},"南希仁":{"weight":1},"黃藥師":{"weight":30},"洪七公":{"weight":8},"華箏":{"weight":1},"梅超風":{"weight":6},"鐵木真":{"weight":1},"程瑤迦":{"weight":5},"王重陽":{"weight":1},"楊康":{"weight":22},"金輪法王":{"weight":1},"歐陽鋒":{"weight":13},"楊鐵心":{"weight":1},"孫不二":{"weight":1},"韓寶駒":{"weight":2},"靈智上人":{"weight":2},"穆念慈":{"weight":2},"侯通海":{"weight":3},"石彥明":{"weight":1},"周伯通":{"weight":8},"黃蓉":{"weight":50},"陸冠英":{"weight":5},"陸乘風":{"weight":1},"丘處機":{"weight":3},"小龍女":{"weight":8},"柯鎮惡":{"weight":10}},"察合台":{"歐陽鋒":{"weight":1},"霍都":{"weight":1},"都史":{"weight":1},"完顏洪烈":{"weight":2},"博爾術":{"weight":5},"魯有腳":{"weight":3},"拖雷":{"weight":9},"華箏":{"weight":3},"木華黎":{"weight":4},"鐵木真":{"weight":14},"黃蓉":{"weight":3},"桑昆":{"weight":4},"哲別":{"weight":4}},"楊鐵心":{"彭連虎":{"weight":8},"都史":{"weight":1},"一燈大師":{"weight":1},"完顏洪烈":{"weight":10},"南希仁":{"weight":1},"黃藥師":{"weight":3},"張阿生":{"weight":1},"錢青健":{"weight":1},"華箏":{"weight":3},"洪七公":{"weight":2},"梅超風":{"weight":1},"王處一":{"weight":11},"蓋運聰":{"weight":1},"鐵木真":{"weight":2},"王道乾":{"weight":3},"程瑤迦":{"weight":1},"王重陽":{"weight":1},"包惜弱":{"weight":31},"歐陽鋒":{"weight":2},"楊康":{"weight":58},"郭襄":{"weight":1},"吳青烈":{"weight":1},"博爾術":{"weight":1},"孫不二":{"weight":1},"韓寶駒":{"weight":1},"郭嘯天":{"weight":39},"靈智上人":{"weight":2},"拖雷":{"weight":3},"穆念慈":{"weight":21},"全金發":{"weight":2},"侯通海":{"weight":9},"李萍":{"weight":5},"黃蓉":{"weight":24},"陸乘風":{"weight":1},"陸冠英":{"weight":1},"丘處機":{"weight":31},"小龍女":{"weight":2},"哲別":{"weight":2},"柯鎮惡":{"weight":5},"沈青剛":{"weight":1},"段天德":{"weight":9},"湯祖德":{"weight":2}},"吳青烈":{"華箏":{"weight":1},"侯通海":{"weight":2},"黃蓉":{"weight":2},"陸冠英":{"weight":1},"哲別":{"weight":1},"柯鎮惡":{"weight":2},"沈青剛":{"weight":5},"拖雷":{"weight":1},"錢青健":{"weight":3}},"張一氓":{"聖因師太":{"weight":6},"武修文":{"weight":1},"人廚子":{"weight":3},"樊一翁":{"weight":1},"韓無垢":{"weight":2},"黃蓉":{"weight":6},"郭襄":{"weight":5},"狗肉頭陀":{"weight":1}},"魯有腳":{"霍都":{"weight":22},"一燈大師":{"weight":4},"完顏洪烈":{"weight":4},"武三通":{"weight":1},"耶律燕":{"weight":1},"黃藥師":{"weight":7},"武敦儒":{"weight":5},"洪七公":{"weight":27},"青靈子":{"weight":1},"華箏":{"weight":4},"梅超風":{"weight":1},"樊一翁":{"weight":1},"王處一":{"weight":1},"鐵木真":{"weight":9},"程瑤迦":{"weight":2},"瑛姑":{"weight":3},"裘千仞":{"weight":12},"金輪法王":{"weight":6},"楊康":{"weight":22},"歐陽鋒":{"weight":17},"武修文":{"weight":5},"郭襄":{"weight":5},"拖雷":{"weight":1},"穆念慈":{"weight":2},"彭長老":{"weight":15},"簡長老":{"weight":17},"余兆興":{"weight":3},"尼摩星":{"weight":1},"周伯通":{"weight":2},"黃蓉":{"weight":74},"陸冠英":{"weight":1},"丘處機":{"weight":6},"小龍女":{"weight":6}},"穆念慈":{"彭連虎":{"weight":3},"一燈大師":{"weight":3},"完顏洪烈":{"weight":13},"武敦儒":{"weight":1},"黃藥師":{"weight":13},"華箏":{"weight":8},"洪七公":{"weight":16},"趙志敬":{"weight":1},"梅超風":{"weight":8},"王處一":{"weight":15},"鐵木真":{"weight":4},"程瑤迦":{"weight":6},"王重陽":{"weight":2},"包惜弱":{"weight":6},"裘千仞":{"weight":5},"歐陽鋒":{"weight":12},"楊康":{"weight":85},"武修文":{"weight":1},"郭襄":{"weight":1},"博爾術":{"weight":1},"韓寶駒":{"weight":1},"孫不二":{"weight":3},"郭嘯天":{"weight":2},"拖雷":{"weight":8},"靈智上人":{"weight":1},"彭長老":{"weight":2},"全金發":{"weight":1},"裘千丈":{"weight":2},"周伯通":{"weight":3},"黃蓉":{"weight":67},"陸冠英":{"weight":8},"陸乘風":{"weight":1},"丘處機":{"weight":28},"小龍女":{"weight":1},"哲別":{"weight":2},"柯鎮惡":{"weight":6},"段天德":{"weight":1},"湯祖德":{"weight":1}},"全金發":{"楊康":{"weight":2},"武修文":{"weight":1},"都史":{"weight":1},"完顏洪烈":{"weight":2},"南希仁":{"weight":2},"韓寶駒":{"weight":2},"張阿生":{"weight":3},"拖雷":{"weight":1},"武敦儒":{"weight":1},"李萍":{"weight":1},"梅超風":{"weight":1},"王處一":{"weight":1},"丘處機":{"weight":4},"包惜弱":{"weight":1},"柯鎮惡":{"weight":4},"焦木大師":{"weight":1},"段天德":{"weight":1}},"李萍":{"楊康":{"weight":4},"都史":{"weight":1},"完顏洪烈":{"weight":1},"韓寶駒":{"weight":4},"張阿生":{"weight":2},"拖雷":{"weight":8},"郭嘯天":{"weight":4},"華箏":{"weight":7},"木華黎":{"weight":1},"鐵木真":{"weight":10},"黃蓉":{"weight":2},"丘處機":{"weight":9},"哲別":{"weight":2},"包惜弱":{"weight":4},"柯鎮惡":{"weight":4},"焦木大師":{"weight":2},"段天德":{"weight":18}},"周伯通":{"李志常":{"weight":4},"霍都":{"weight":2},"黃裳":{"weight":7},"一燈大師":{"weight":63},"完顏洪烈":{"weight":19},"南希仁":{"weight":2},"武三通":{"weight":3},"黃藥師":{"weight":138},"耶律燕":{"weight":1},"華箏":{"weight":1},"梅超風":{"weight":25},"程瑤迦":{"weight":2},"馬光佐":{"weight":10},"呂文德":{"weight":1},"楊康":{"weight":12},"武修文":{"weight":1},"孫不二":{"weight":5},"黃夫人":{"weight":4},"耶律楚材":{"weight":1},"侯通海":{"weight":5},"小龍女":{"weight":84},"柯鎮惡":{"weight":10},"彭連虎":{"weight":15},"速不台":{"weight":1},"武敦儒":{"weight":1},"洪七公":{"weight":88},"趙志敬":{"weight":30},"樊一翁":{"weight":14},"王處一":{"weight":22},"鐵木真":{"weight":6},"瑛姑":{"weight":61},"王重陽":{"weight":23},"林朝英":{"weight":1},"裘千仞":{"weight":38},"歐陽鋒":{"weight":120},"金輪法王":{"weight":82},"郭襄":{"weight":45},"瀟湘子":{"weight":21},"尹克西":{"weight":17},"韓寶駒":{"weight":1},"靈智上人":{"weight":17},"拖雷":{"weight":2},"彭長老":{"weight":1},"裘千丈":{"weight":2},"尼摩星":{"weight":10},"黃蓉":{"weight":189},"陸冠英":{"weight":4},"陸乘風":{"weight":3},"丘處機":{"weight":51},"大頭鬼":{"weight":1},"哲別":{"weight":1},"郭破虜":{"weight":1},"公孫止":{"weight":13}},"木華黎":{"華箏":{"weight":1},"速不台":{"weight":2},"完顏洪熙":{"weight":5},"都史":{"weight":3},"鐵木真":{"weight":14},"完顏洪烈":{"weight":6},"博爾術":{"weight":7},"桑昆":{"weight":7},"哲別":{"weight":6},"拖雷":{"weight":8}},"尼摩星":{"歐陽鋒":{"weight":2},"金輪法王":{"weight":86},"達爾巴":{"weight":5},"霍都":{"weight":4},"武修文":{"weight":1},"郭襄":{"weight":17},"瀟湘子":{"weight":66},"一燈大師":{"weight":3},"尹克西":{"weight":42},"馮默風":{"weight":1},"武三通":{"weight":1},"武敦儒":{"weight":1},"聾啞頭陀":{"weight":1},"洪七公":{"weight":1},"趙志敬":{"weight":9},"樊一翁":{"weight":3},"王處一":{"weight":1},"黃蓉":{"weight":6},"馬光佐":{"weight":21},"小龍女":{"weight":36},"瑛姑":{"weight":1},"公孫止":{"weight":2},"裘千仞":{"weight":1}},"黃蓉":{"李志常":{"weight":3},"聖因師太":{"weight":7},"霍都":{"weight":61},"黃裳":{"weight":2},"完顏洪烈":{"weight":73},"王志坦":{"weight":1},"一燈大師":{"weight":117},"南希仁":{"weight":19},"武三娘":{"weight":3},"武三通":{"weight":33},"耶律燕":{"weight":10},"黃藥師":{"weight":280},"華箏":{"weight":35},"梅超風":{"weight":90},"程瑤迦":{"weight":25},"呂文德":{"weight":10},"樵夫":{"weight":1},"天竺神僧":{"weight":1},"楊康":{"weight":165},"武修文":{"weight":29},"張志仙":{"weight":1},"馮默風":{"weight":1},"孫不二":{"weight":23},"黃夫人":{"weight":4},"郭嘯天":{"weight":3},"余兆興":{"weight":4},"簡長老":{"weight":26},"侯通海":{"weight":50},"石彥明":{"weight":1},"喬寨主":{"weight":1},"小龍女":{"weight":183},"柯鎮惡":{"weight":90},"段天德":{"weight":1},"彭連虎":{"weight":61},"人廚子":{"weight":3},"武敦儒":{"weight":11},"張阿生":{"weight":3},"錢青健":{"weight":4},"洪七公":{"weight":309},"趙志敬":{"weight":17},"樊一翁":{"weight":5},"王處一":{"weight":37},"鐵木真":{"weight":29},"王重陽":{"weight":36},"瑛姑":{"weight":70},"點蒼漁隱":{"weight":4},"包惜弱":{"weight":4},"林朝英":{"weight":4},"裘千仞":{"weight":113},"歐陽鋒":{"weight":315},"金輪法王":{"weight":108},"達爾巴":{"weight":15},"洪凌波":{"weight":3},"郭襄":{"weight":141},"瀟湘子":{"weight":4},"博爾術":{"weight":3},"尹克西":{"weight":1},"韓寶駒":{"weight":27},"狗肉頭陀":{"weight":1},"靈智上人":{"weight":27},"拖雷":{"weight":27},"聾啞頭陀":{"weight":4},"彭長老":{"weight":18},"裘千丈":{"weight":12},"韓無垢":{"weight":3},"陸乘風":{"weight":23},"陸冠英":{"weight":57},"大頭鬼":{"weight":3},"丘處機":{"weight":67},"簡管家":{"weight":7},"祁志誠":{"weight":1},"哲別":{"weight":9},"郭破虜":{"weight":8},"沈青剛":{"weight":3},"蒙哥":{"weight":1},"何沅君":{"weight":2},"公孫止":{"weight":36}},"大頭鬼":{"史季強":{"weight":5},"金輪法王":{"weight":8},"喪門鬼":{"weight":1},"吊死鬼":{"weight":2},"霍都":{"weight":1},"樊一翁":{"weight":13},"郭襄":{"weight":26},"笑臉鬼":{"weight":1},"黃藥師":{"weight":1},"史仲猛":{"weight":1}},"哲別":{"速不台":{"weight":3},"都史":{"weight":1},"完顏洪烈":{"weight":9},"南希仁":{"weight":1},"黃藥師":{"weight":2},"錢青健":{"weight":1},"華箏":{"weight":12},"梅超風":{"weight":1},"完顏洪熙":{"weight":6},"王處一":{"weight":1},"鐵木真":{"weight":33},"桑昆":{"weight":12},"裘千仞":{"weight":2},"楊康":{"weight":5},"金輪法王":{"weight":1},"歐陽鋒":{"weight":3},"博爾術":{"weight":19},"韓寶駒":{"weight":1},"孫不二":{"weight":1},"拖雷":{"weight":22},"陸冠英":{"weight":1},"丘處機":{"weight":3},"柯鎮惡":{"weight":1},"沈青剛":{"weight":1},"段天德":{"weight":1}},"祁志誠":{"李志常":{"weight":4},"彭連虎":{"weight":1},"趙志敬":{"weight":10},"王處一":{"weight":1},"鐵木真":{"weight":1},"張志仙":{"weight":1},"王志坦":{"weight":5},"丘處機":{"weight":4},"小龍女":{"weight":5},"孫不二":{"weight":1},"裘千仞":{"weight":1}},"郭破虜":{"霍都":{"weight":1},"郭襄":{"weight":12},"丘處機":{"weight":2},"小龍女":{"weight":1},"呂文德":{"weight":1},"韓寶駒":{"weight":1},"黃藥師":{"weight":1}},"沈青剛":{"彭連虎":{"weight":1},"華箏":{"weight":1},"侯通海":{"weight":3},"陸冠英":{"weight":1},"柯鎮惡":{"weight":1},"拖雷":{"weight":1},"錢青健":{"weight":3}},"蒙哥":{"金輪法王":{"weight":1},"樊一翁":{"weight":1},"鐵木真":{"weight":3},"郭襄":{"weight":1},"柯鎮惡":{"weight":1},"拖雷":{"weight":2}},"何沅君":{"小龍女":{"weight":1},"武三娘":{"weight":6},"武三通":{"weight":7},"柯鎮惡":{"weight":1},"陸二娘":{"weight":2}},"湯祖德":{"楊康":{"weight":3},"王處一":{"weight":3},"完顏洪烈":{"weight":2},"包惜弱":{"weight":1}},"李志常":{"彭連虎":{"weight":1},"達爾巴":{"weight":2},"霍都":{"weight":2},"瀟湘子":{"weight":4},"郭襄":{"weight":1},"張志仙":{"weight":1},"王志坦":{"weight":17},"武三通":{"weight":1},"孫不二":{"weight":1},"黃藥師":{"weight":2},"華箏":{"weight":1},"趙志敬":{"weight":18},"王處一":{"weight":3},"程瑤迦":{"weight":1},"鐵木真":{"weight":1},"陸冠英":{"weight":1},"丘處機":{"weight":10},"瑛姑":{"weight":1},"小龍女":{"weight":2},"申志凡":{"weight":1},"裘千仞":{"weight":1}},"聖因師太":{"武修文":{"weight":1},"樊一翁":{"weight":1},"人廚子":{"weight":3},"韓無垢":{"weight":3},"郭襄":{"weight":6},"狗肉頭陀":{"weight":1}},"霍都":{"煞神鬼":{"weight":1},"一燈大師":{"weight":3},"武三通":{"weight":1},"黃藥師":{"weight":4},"武敦儒":{"weight":1},"青靈子":{"weight":4},"洪七公":{"weight":11},"趙志敬":{"weight":4},"樊一翁":{"weight":2},"王處一":{"weight":2},"鐵木真":{"weight":2},"馬光佐":{"weight":1},"王重陽":{"weight":1},"瑛姑":{"weight":1},"點蒼漁隱":{"weight":3},"史仲猛":{"weight":1},"楊康":{"weight":1},"金輪法王":{"weight":38},"歐陽鋒":{"weight":4},"達爾巴":{"weight":46},"武修文":{"weight":1},"郭襄":{"weight":10},"瀟湘子":{"weight":4},"尹克西":{"weight":1},"孫不二":{"weight":3},"拖雷":{"weight":1},"彭長老":{"weight":1},"陸冠英":{"weight":2},"丘處機":{"weight":10},"小龍女":{"weight":26}},"柯辟邪":{"梅超風":{"weight":3},"陸乘風":{"weight":1},"柯鎮惡":{"weight":2}},"黃裳":{"金輪法王":{"weight":1},"梅超風":{"weight":2},"完顏洪烈":{"weight":1},"王重陽":{"weight":1},"黃藥師":{"weight":4}},"都史":{"楊康":{"weight":1},"完顏洪烈":{"weight":4},"博爾術":{"weight":1},"韓寶駒":{"weight":3},"拖雷":{"weight":12},"黃藥師":{"weight":1},"張阿生":{"weight":1},"華箏":{"weight":8},"梅超風":{"weight":1},"完顏洪熙":{"weight":1},"鐵木真":{"weight":16},"丘處機":{"weight":2},"桑昆":{"weight":15},"包惜弱":{"weight":1},"柯鎮惡":{"weight":3},"段天德":{"weight":1}},"皮清玄":{"姬清虛":{"weight":6},"申志凡":{"weight":3}},"一燈大師":{"武三娘":{"weight":2},"武三通":{"weight":15},"武敦儒":{"weight":1},"耶律燕":{"weight":3},"黃藥師":{"weight":63},"華箏":{"weight":2},"洪七公":{"weight":53},"梅超風":{"weight":4},"王處一":{"weight":4},"鐵木真":{"weight":2},"王重陽":{"weight":19},"瑛姑":{"weight":52},"點蒼漁隱":{"weight":3},"呂文德":{"weight":1},"樵夫":{"weight":1},"天竺神僧":{"weight":1},"裘千仞":{"weight":47},"金輪法王":{"weight":14},"歐陽鋒":{"weight":57},"楊康":{"weight":5},"達爾巴":{"weight":2},"武修文":{"weight":3},"洪凌波":{"weight":1},"郭襄":{"weight":24},"瀟湘子":{"weight":1},"尹克西":{"weight":1},"孫不二":{"weight":1},"黃夫人":{"weight":1},"拖雷":{"weight":2},"彭長老":{"weight":3},"裘千丈":{"weight":1},"喬寨主":{"weight":1},"陸乘風":{"weight":1},"陸冠英":{"weight":1},"丘處機":{"weight":10},"小龍女":{"weight":14},"柯鎮惡":{"weight":5},"公孫止":{"weight":1}},"完顏洪烈":{"彭連虎":{"weight":31},"南希仁":{"weight":5},"張阿生":{"weight":3},"黃藥師":{"weight":18},"華箏":{"weight":7},"洪七公":{"weight":14},"梅超風":{"weight":8},"完顏洪熙":{"weight":14},"蓋運聰":{"weight":2},"王處一":{"weight":7},"王道乾":{"weight":1},"鐵木真":{"weight":34},"王重陽":{"weight":1},"桑昆":{"weight":15},"瑛姑":{"weight":1},"包惜弱":{"weight":20},"焦木大師":{"weight":3},"裘千仞":{"weight":9},"歐陽鋒":{"weight":43},"楊康":{"weight":61},"博爾術":{"weight":3},"韓寶駒":{"weight":8},"靈智上人":{"weight":19},"拖雷":{"weight":10},"郭嘯天":{"weight":5},"余兆興":{"weight":1},"裘千丈":{"weight":1},"侯通海":{"weight":14},"陸乘風":{"weight":4},"陸冠英":{"weight":1},"簡管家":{"weight":1},"丘處機":{"weight":28},"柯鎮惡":{"weight":14},"段天德":{"weight":6}},"王志坦":{"彭連虎":{"weight":1},"趙志敬":{"weight":18},"王處一":{"weight":1},"瀟湘子":{"weight":4},"鐵木真":{"weight":1},"張志仙":{"weight":1},"丘處機":{"weight":4},"孫不二":{"weight":1},"申志凡":{"weight":1},"裘千仞":{"weight":1}},"南希仁":{"楊康":{"weight":5},"彭連虎":{"weight":4},"歐陽鋒":{"weight":8},"韓寶駒":{"weight":33},"孫不二":{"weight":1},"黃藥師":{"weight":6},"張阿生":{"weight":20},"拖雷":{"weight":4},"錢青健":{"weight":1},"華箏":{"weight":1},"洪七公":{"weight":1},"侯通海":{"weight":2},"梅超風":{"weight":19},"王處一":{"weight":1},"鐵木真":{"weight":2},"陸乘風":{"weight":1},"丘處機":{"weight":14},"王重陽":{"weight":2},"柯鎮惡":{"weight":28},"焦木大師":{"weight":1},"段天德":{"weight":1},"裘千仞":{"weight":3}},"武三娘":{"武修文":{"weight":2},"梅超風":{"weight":1},"洪凌波":{"weight":2},"柯鎮惡":{"weight":11},"武三通":{"weight":14},"陸二娘":{"weight":8},"武敦儒":{"weight":2}},"武三通":{"歐陽鋒":{"weight":1},"金輪法王":{"weight":2},"武修文":{"weight":19},"洪凌波":{"weight":1},"郭襄":{"weight":5},"黃藥師":{"weight":3},"耶律燕":{"weight":6},"武敦儒":{"weight":16},"洪七公":{"weight":1},"樊一翁":{"weight":1},"程瑤迦":{"weight":1},"陸冠英":{"weight":1},"丘處機":{"weight":1},"瑛姑":{"weight":1},"小龍女":{"weight":22},"點蒼漁隱":{"weight":1},"陸二娘":{"weight":3},"柯鎮惡":{"weight":2},"公孫止":{"weight":10},"天竺神僧":{"weight":1},"裘千仞":{"weight":7}},"獨孤求敗":{"金輪法王":{"weight":1},"小龍女":{"weight":1},"裘千仞":{"weight":1}},"黃藥師":{"彭連虎":{"weight":14},"武敦儒":{"weight":2},"張阿生":{"weight":3},"耶律燕":{"weight":1},"華箏":{"weight":15},"洪七公":{"weight":149},"趙志敬":{"weight":2},"梅超風":{"weight":60},"王處一":{"weight":21},"鐵木真":{"weight":6},"程瑤迦":{"weight":19},"桑昆":{"weight":1},"瑛姑":{"weight":16},"王重陽":{"weight":37},"呂文德":{"weight":2},"裘千仞":{"weight":33},"歐陽鋒":{"weight":167},"金輪法王":{"weight":25},"楊康":{"weight":34},"達爾巴":{"weight":1},"武修文":{"weight":6},"洪凌波":{"weight":1},"郭襄":{"weight":29},"瀟湘子":{"weight":6},"博爾術":{"weight":2},"尹克西":{"weight":6},"馮默風":{"weight":6},"韓寶駒":{"weight":14},"孫不二":{"weight":14},"黃夫人":{"weight":6},"靈智上人":{"weight":12},"拖雷":{"weight":11},"彭長老":{"weight":1},"簡長老":{"weight":2},"耶律楚材":{"weight":1},"裘千丈":{"weight":3},"侯通海":{"weight":7},"陸冠英":{"weight":26},"陸乘風":{"weight":19},"丘處機":{"weight":50},"小龍女":{"weight":21},"柯鎮惡":{"weight":44},"公孫止":{"weight":2}},"耶律燕":{"耶律楚材":{"weight":3},"梅超風":{"weight":1},"武修文":{"weight":6},"鐵木真":{"weight":1},"小龍女":{"weight":2},"武敦儒":{"weight":8},"公孫止":{"weight":2},"裘千仞":{"weight":1}},"華箏":{"張阿生":{"weight":1},"錢青健":{"weight":1},"洪七公":{"weight":3},"梅超風":{"weight":7},"王處一":{"weight":4},"鐵木真":{"weight":29},"瑛姑":{"weight":2},"桑昆":{"weight":8},"包惜弱":{"weight":1},"裘千仞":{"weight":4},"楊康":{"weight":10},"歐陽鋒":{"weight":8},"郭襄":{"weight":1},"博爾術":{"weight":6},"韓寶駒":{"weight":4},"孫不二":{"weight":4},"拖雷":{"weight":36},"郭嘯天":{"weight":1},"彭長老":{"weight":1},"簡長老":{"weight":1},"陸冠英":{"weight":1},"丘處機":{"weight":17},"小龍女":{"weight":1},"柯鎮惡":{"weight":4},"段天德":{"weight":2}},"青靈子":{"達爾巴":{"weight":5},"郭襄":{"weight":3},"聾啞頭陀":{"weight":1}},"梅超風":{"彭連虎":{"weight":15},"張阿生":{"weight":15},"洪七公":{"weight":18},"王處一":{"weight":11},"程瑤迦":{"weight":1},"鐵木真":{"weight":4},"王重陽":{"weight":8},"瑛姑":{"weight":2},"桑昆":{"weight":3},"裘千仞":{"weight":14},"楊康":{"weight":21},"歐陽鋒":{"weight":18},"博爾術":{"weight":1},"韓寶駒":{"weight":34},"馮默風":{"weight":2},"孫不二":{"weight":9},"拖雷":{"weight":3},"黃夫人":{"weight":3},"靈智上人":{"weight":3},"簡長老":{"weight":1},"侯通海":{"weight":10},"陸冠英":{"weight":12},"陸乘風":{"weight":19},"丘處機":{"weight":23},"小龍女":{"weight":1},"柯鎮惡":{"weight":39}},"蓋運聰":{"包惜弱":{"weight":1}},"程瑤迦":{"楊康":{"weight":7},"彭連虎":{"weight":4},"歐陽鋒":{"weight":3},"孫不二":{"weight":5},"余兆興":{"weight":1},"洪七公":{"weight":2},"趙志敬":{"weight":1},"侯通海":{"weight":12},"王處一":{"weight":1},"陸乘風":{"weight":2},"陸冠英":{"weight":43},"丘處機":{"weight":4},"王重陽":{"weight":2},"柯鎮惡":{"weight":1}},"王道乾":{"丘處機":{"weight":4},"包惜弱":{"weight":1},"郭嘯天":{"weight":3}},"馬光佐":{"金輪法王":{"weight":32},"達爾巴":{"weight":1},"樊一翁":{"weight":10},"瀟湘子":{"weight":27},"瑛姑":{"weight":1},"小龍女":{"weight":10},"尹克西":{"weight":19},"公孫止":{"weight":7}},"呂文德":{"金輪法王":{"weight":2},"鐵木真":{"weight":1},"郭襄":{"weight":1},"小龍女":{"weight":1}},"樵夫":{"瑛姑":{"weight":2}},"申志凡":{"洪七公":{"weight":1},"趙志敬":{"weight":2},"丘處機":{"weight":1},"小龍女":{"weight":1},"姬清虛":{"weight":9}},"史仲猛":{"史季強":{"weight":7},"金輪法王":{"weight":1},"吊死鬼":{"weight":1},"喪門鬼":{"weight":2},"樊一翁":{"weight":2},"煞神鬼":{"weight":1},"討債鬼":{"weight":1},"郭襄":{"weight":3},"笑臉鬼":{"weight":1}},"天竺神僧":{"小龍女":{"weight":3},"點蒼漁隱":{"weight":1},"裘千仞":{"weight":1}},"楊康":{"彭連虎":{"weight":36},"張阿生":{"weight":3},"錢青健":{"weight":1},"洪七公":{"weight":31},"王處一":{"weight":33},"鐵木真":{"weight":8},"王重陽":{"weight":2},"瑛姑":{"weight":1},"包惜弱":{"weight":14},"裘千仞":{"weight":24},"歐陽鋒":{"weight":49},"郭襄":{"weight":1},"博爾術":{"weight":3},"韓寶駒":{"weight":7},"孫不二":{"weight":5},"靈智上人":{"weight":13},"郭嘯天":{"weight":8},"拖雷":{"weight":14},"彭長老":{"weight":13},"余兆興":{"weight":1},"簡長老":{"weight":13},"耶律楚材":{"weight":1},"裘千丈":{"weight":2},"侯通海":{"weight":16},"陸乘風":{"weight":7},"陸冠英":{"weight":22},"丘處機":{"weight":45},"簡管家":{"weight":5},"小龍女":{"weight":3},"柯鎮惡":{"weight":29},"段天德":{"weight":5}},"武修文":{"歐陽鋒":{"weight":8},"金輪法王":{"weight":10},"達爾巴":{"weight":1},"郭襄":{"weight":5},"瀟湘子":{"weight":2},"尹克西":{"weight":1},"武敦儒":{"weight":65},"洪七公":{"weight":1},"韓無垢":{"weight":1},"小龍女":{"weight":9},"陸二娘":{"weight":1},"柯鎮惡":{"weight":2},"公孫止":{"weight":4}},"討債鬼":{"喪門鬼":{"weight":1}},"張志仙":{"彭連虎":{"weight":1},"趙志敬":{"weight":1},"王處一":{"weight":1},"孫不二":{"weight":1},"裘千仞":{"weight":1}},"孫不二":{"歐陽鋒":{"weight":5},"彭連虎":{"weight":2},"金輪法王":{"weight":3},"博爾術":{"weight":1},"拖雷":{"weight":3},"余兆興":{"weight":1},"洪七公":{"weight":5},"趙志敬":{"weight":11},"侯通海":{"weight":2},"王處一":{"weight":18},"陸乘風":{"weight":1},"陸冠英":{"weight":5},"丘處機":{"weight":28},"王重陽":{"weight":8},"小龍女":{"weight":10},"點蒼漁隱":{"weight":1},"柯鎮惡":{"weight":5},"段天德":{"weight":1},"裘千仞":{"weight":2}},"馮默風":{"金輪法王":{"weight":6},"樊一翁":{"weight":1},"瀟湘子":{"weight":3},"陸乘風":{"weight":2},"小龍女":{"weight":1}},"郭嘯天":{"陸乘風":{"weight":2},"丘處機":{"weight":14},"小龍女":{"weight":2},"包惜弱":{"weight":10},"韓寶駒":{"weight":2},"柯鎮惡":{"weight":2},"焦木大師":{"weight":1},"段天德":{"weight":7},"拖雷":{"weight":1},"張阿生":{"weight":1}},"黃夫人":{"洪七公":{"weight":3},"歐陽鋒":{"weight":5},"陸乘風":{"weight":1},"丘處機":{"weight":1},"拖雷":{"weight":1},"裘千仞":{"weight":1}},"簡長老":{"歐陽鋒":{"weight":3},"洪七公":{"weight":9},"丘處機":{"weight":1},"瑛姑":{"weight":1},"彭長老":{"weight":11},"余兆興":{"weight":1},"裘千仞":{"weight":7}},"余兆興":{"洪七公":{"weight":4},"彭長老":{"weight":1},"裘千仞":{"weight":1}},"耶律楚材":{"歐陽鋒":{"weight":1},"鐵木真":{"weight":4},"丘處機":{"weight":2},"柯鎮惡":{"weight":1}},"侯通海":{"歐陽鋒":{"weight":10},"彭連虎":{"weight":44},"韓寶駒":{"weight":2},"靈智上人":{"weight":13},"錢青健":{"weight":2},"洪七公":{"weight":4},"王處一":{"weight":11},"鐵木真":{"weight":1},"陸冠英":{"weight":13},"丘處機":{"weight":12},"簡管家":{"weight":1},"柯鎮惡":{"weight":3},"裘千仞":{"weight":1}},"喪門鬼":{"史季強":{"weight":1},"吊死鬼":{"weight":1},"樊一翁":{"weight":2},"笑臉鬼":{"weight":2}},"小龍女":{"武敦儒":{"weight":4},"洪七公":{"weight":10},"趙志敬":{"weight":92},"樊一翁":{"weight":7},"王處一":{"weight":9},"鐵木真":{"weight":1},"瑛姑":{"weight":1},"王重陽":{"weight":36},"點蒼漁隱":{"weight":3},"林朝英":{"weight":50},"裘千仞":{"weight":16},"歐陽鋒":{"weight":21},"金輪法王":{"weight":159},"達爾巴":{"weight":14},"洪凌波":{"weight":30},"郭襄":{"weight":72},"瀟湘子":{"weight":40},"尹克西":{"weight":29},"韓寶駒":{"weight":1},"彭長老":{"weight":6},"裘千丈":{"weight":1},"丘處機":{"weight":37},"柯鎮惡":{"weight":1},"姬清虛":{"weight":2},"公孫止":{"weight":98}},"柯鎮惡":{"歐陽鋒":{"weight":55},"彭連虎":{"weight":20},"金輪法王":{"weight":1},"郭襄":{"weight":6},"韓寶駒":{"weight":49},"張阿生":{"weight":27},"靈智上人":{"weight":6},"拖雷":{"weight":4},"錢青健":{"weight":2},"洪七公":{"weight":23},"趙志敬":{"weight":1},"王處一":{"weight":12},"鐵木真":{"weight":6},"陸冠英":{"weight":4},"陸乘風":{"weight":4},"丘處機":{"weight":54},"桑昆":{"weight":3},"王重陽":{"weight":6},"瑛姑":{"weight":1},"包惜弱":{"weight":3},"陸二娘":{"weight":1},"焦木大師":{"weight":7},"段天德":{"weight":8},"裘千仞":{"weight":8}},"陸二娘":{"武敦儒":{"weight":1}},"笑臉鬼":{"史季強":{"weight":5},"吊死鬼":{"weight":5},"樊一翁":{"weight":3},"郭襄":{"weight":3}},"段天德":{"王處一":{"weight":1},"鐵木真":{"weight":1},"陸冠英":{"weight":1},"陸乘風":{"weight":3},"丘處機":{"weight":19},"博爾術":{"weight":1},"包惜弱":{"weight":8},"韓寶駒":{"weight":8},"焦木大師":{"weight":2},"張阿生":{"weight":3},"拖雷":{"weight":4}},"姬清虛":{"洪七公":{"weight":1}},"彭連虎":{"歐陽鋒":{"weight":26},"韓寶駒":{"weight":4},"張阿生":{"weight":1},"靈智上人":{"weight":30},"錢青健":{"weight":1},"洪七公":{"weight":14},"裘千丈":{"weight":1},"趙志敬":{"weight":1},"王處一":{"weight":15},"鐵木真":{"weight":1},"陸冠英":{"weight":4},"丘處機":{"weight":27},"簡管家":{"weight":1},"王重陽":{"weight":2},"包惜弱":{"weight":2},"焦木大師":{"weight":1},"裘千仞":{"weight":7}},"人廚子":{"樊一翁":{"weight":1},"韓無垢":{"weight":1},"郭襄":{"weight":5},"狗肉頭陀":{"weight":1}},"速不台":{"歐陽鋒":{"weight":1},"鐵木真":{"weight":4},"博爾術":{"weight":2},"拖雷":{"weight":1},"裘千仞":{"weight":1}},"煞神鬼":{"史季強":{"weight":1},"樊一翁":{"weight":1}},"武敦儒":{"歐陽鋒":{"weight":1},"金輪法王":{"weight":4},"趙志敬":{"weight":1},"洪凌波":{"weight":1},"郭襄":{"weight":1},"瀟湘子":{"weight":1},"尹克西":{"weight":1},"公孫止":{"weight":3}},"張阿生":{"歐陽鋒":{"weight":1},"鐵木真":{"weight":1},"丘處機":{"weight":19},"包惜弱":{"weight":1},"韓寶駒":{"weight":27},"焦木大師":{"weight":5},"拖雷":{"weight":4}},"錢青健":{"王處一":{"weight":1},"陸冠英":{"weight":1},"靈智上人":{"weight":1},"拖雷":{"weight":1}},"洪七公":{"歐陽鋒":{"weight":248},"金輪法王":{"weight":17},"達爾巴":{"weight":5},"郭襄":{"weight":5},"韓寶駒":{"weight":3},"靈智上人":{"weight":14},"拖雷":{"weight":4},"彭長老":{"weight":7},"裘千丈":{"weight":2},"趙志敬":{"weight":1},"王處一":{"weight":15},"鐵木真":{"weight":4},"陸乘風":{"weight":5},"陸冠英":{"weight":3},"丘處機":{"weight":30},"王重陽":{"weight":32},"瑛姑":{"weight":13},"包惜弱":{"weight":1},"林朝英":{"weight":1},"裘千仞":{"weight":29}},"趙志敬":{"金輪法王":{"weight":36},"歐陽鋒":{"weight":4},"達爾巴":{"weight":1},"洪凌波":{"weight":1},"郭襄":{"weight":1},"瀟湘子":{"weight":14},"尹克西":{"weight":7},"拖雷":{"weight":1},"王處一":{"weight":12},"鐵木真":{"weight":3},"陸冠英":{"weight":1},"丘處機":{"weight":28},"王重陽":{"weight":10},"林朝英":{"weight":6},"裘千仞":{"weight":1}},"樊一翁":{"史季強":{"weight":5},"金輪法王":{"weight":13},"吊死鬼":{"weight":2},"鐵木真":{"weight":1},"郭襄":{"weight":15},"瀟湘子":{"weight":17},"尹克西":{"weight":1},"公孫止":{"weight":16}},"完顏洪熙":{"鐵木真":{"weight":17},"丘處機":{"weight":1},"桑昆":{"weight":9},"博爾術":{"weight":1},"拖雷":{"weight":4}},"王處一":{"歐陽鋒":{"weight":13},"金輪法王":{"weight":1},"達爾巴":{"weight":1},"博爾術":{"weight":1},"拖雷":{"weight":2},"靈智上人":{"weight":8},"彭長老":{"weight":1},"裘千丈":{"weight":1},"鐵木真":{"weight":1},"陸冠英":{"weight":1},"陸乘風":{"weight":1},"丘處機":{"weight":73},"簡管家":{"weight":1},"王重陽":{"weight":11},"瑛姑":{"weight":1},"包惜弱":{"weight":2},"裘千仞":{"weight":4}},"忽都虎":{"鐵木真":{"weight":2}},"鐵木真":{"歐陽鋒":{"weight":11},"金輪法王":{"weight":3},"瀟湘子":{"weight":1},"丘處機":{"weight":21},"博爾術":{"weight":16},"瑛姑":{"weight":1},"桑昆":{"weight":33},"尹克西":{"weight":1},"韓寶駒":{"weight":2},"拖雷":{"weight":55},"靈智上人":{"weight":1},"裘千仞":{"weight":3}},"瑛姑":{"歐陽鋒":{"weight":11},"金輪法王":{"weight":5},"裘千丈":{"weight":1},"郭襄":{"weight":18},"瀟湘子":{"weight":1},"陸乘風":{"weight":2},"丘處機":{"weight":2},"王重陽":{"weight":2},"尹克西":{"weight":1},"裘千仞":{"weight":33}},"王重陽":{"歐陽鋒":{"weight":34},"金輪法王":{"weight":1},"洪凌波":{"weight":1},"郭襄":{"weight":3},"韓寶駒":{"weight":1},"彭長老":{"weight":1},"裘千丈":{"weight":2},"陸乘風":{"weight":1},"陸冠英":{"weight":3},"丘處機":{"weight":27},"林朝英":{"weight":27},"公孫止":{"weight":1},"裘千仞":{"weight":8}},"桑昆":{"丘處機":{"weight":2},"博爾術":{"weight":4},"韓寶駒":{"weight":2},"拖雷":{"weight":9}},"點蒼漁隱":{"金輪法王":{"weight":3},"達爾巴":{"weight":8},"裘千仞":{"weight":2}},"包惜弱":{"丘處機":{"weight":16},"韓寶駒":{"weight":1},"焦木大師":{"weight":1},"拖雷":{"weight":2}},"林朝英":{"金輪法王":{"weight":1},"達爾巴":{"weight":1},"洪凌波":{"weight":1},"郭襄":{"weight":1},"丘處機":{"weight":2}},"焦木大師":{"丘處機":{"weight":10},"韓寶駒":{"weight":5}},"裘千仞":{"金輪法王":{"weight":2},"歐陽鋒":{"weight":40},"瀟湘子":{"weight":1},"郭襄":{"weight":15},"博爾術":{"weight":1},"尹克西":{"weight":2},"韓寶駒":{"weight":3},"靈智上人":{"weight":3},"拖雷":{"weight":5},"彭長老":{"weight":12},"裘千丈":{"weight":10},"陸乘風":{"weight":4},"陸冠英":{"weight":9},"丘處機":{"weight":12},"公孫止":{"weight":10}},"金輪法王":{"歐陽鋒":{"weight":10},"裘千丈":{"weight":1},"達爾巴":{"weight":43},"郭襄":{"weight":88},"瀟湘子":{"weight":78},"丘處機":{"weight":8},"尹克西":{"weight":41},"拖雷":{"weight":2},"靈智上人":{"weight":1},"公孫止":{"weight":24}},"歐陽鋒":{"達爾巴":{"weight":2},"裘千丈":{"weight":4},"郭襄":{"weight":5},"瀟湘子":{"weight":1},"陸乘風":{"weight":3},"陸冠英":{"weight":5},"丘處機":{"weight":29},"博爾術":{"weight":2},"韓寶駒":{"weight":5},"拖雷":{"weight":9},"靈智上人":{"weight":22},"彭長老":{"weight":1}},"史季強":{"吊死鬼":{"weight":7},"郭襄":{"weight":4}},"達爾巴":{"郭襄":{"weight":2},"瀟湘子":{"weight":5},"陸冠英":{"weight":1},"丘處機":{"weight":7},"尹克西":{"weight":1},"公孫止":{"weight":1}},"吊死鬼":{"郭襄":{"weight":2}},"郭襄":{"韓無垢":{"weight":4},"瀟湘子":{"weight":1},"丘處機":{"weight":3},"尹克西":{"weight":2},"韓寶駒":{"weight":1},"狗肉頭陀":{"weight":1},"聾啞頭陀":{"weight":3}},"瀟湘子":{"丘處機":{"weight":1},"尹克西":{"weight":75},"拖雷":{"weight":1},"公孫止":{"weight":9}},"博爾術":{"丘處機":{"weight":2},"拖雷":{"weight":10}},"尹克西":{"丘處機":{"weight":1},"拖雷":{"weight":1},"公孫止":{"weight":7}},"韓寶駒":{"陸乘風":{"weight":2},"陸冠英":{"weight":1},"丘處機":{"weight":28},"拖雷":{"weight":4}},"狗肉頭陀":{"韓無垢":{"weight":1}},"拖雷":{"陸冠英":{"weight":1},"丘處機":{"weight":8}},"靈智上人":{"陸乘風":{"weight":1},"簡管家":{"weight":1},"丘處機":{"weight":6}},"彭長老":{"丘處機":{"weight":1}},"裘千丈":{"丘處機":{"weight":2},"公孫止":{"weight":1}},"陸冠英":{"陸乘風":{"weight":9},"丘處機":{"weight":9}},"陸乘風":{"丘處機":{"weight":2}},"丘處機":{"公孫止":{"weight":1}}}}